Workbook
Name SegmentaciónDeDatos_ALERTA_VENC.: #N/A
Name SegmentaciónDeDatos_AREA: #N/A
Name SegmentaciónDeDatos_ESTADO_SEGÚN_MORA: #N/A
Name SegmentaciónDeDatos_MES: #N/A
Name SegmentaciónDeDatos_PROVINCIA: #N/A

Sheet TABLERO COBRANZAS

Sheet CLIENTES
A1: ID Cliente | B1: Nombre Cliente | C1: Provincia
A2: Cliente 1 | B2: Cliente 1 | C2: Jujuy
A3: Cliente 2 | B3: Cliente 2 | C3: Santiago del Estero
A4: Cliente 3 | B4: Cliente 3 | C4: Catamarca
A5: Cliente 4 | B5: Cliente 4 | C5: Catamarca
A6: Cliente 5 | B6: Cliente 5 | C6: Jujuy
A7: Cliente 6 | B7: Cliente 6 | C7: Salta
A8: Cliente 7 | B8: Cliente 7 | C8: Catamarca
A9: Cliente 8 | B9: Cliente 8 | C9: Catamarca
A10: Cliente 9 | B10: Cliente 9 | C10: Catamarca
A11: Cliente 10 | B11: Cliente 10 | C11: Tucuman
A12: Cliente 11 | B12: Cliente 11 | C12: Catamarca
... A61: Cliente 60 | B61: Cliente 60 | C61: Tucuman

Sheet COTIZACION
A1: Fecha | B1: Cotizacion
A2: 45870 | B2: 1380
A3: 45873 | B3: 1375
A4: 45874 | B4: 1370
A5: 45875 | B5: 1350
A6: 45876 | B6: 1345
A7: 45877 | B7: 1340
A8: 45880 | B8: 1335
A9: 45881 | B9: 1335
A10: 45882 | B10: 1330
A11: 45883 | B11: 1325
A12: 45884 | B12: 1310
A13: 45887 | B13: 1310
... A160: 46076 | B160: 1395

Sheet DETALLES
A3: TIPO DE FACTURA | B3: SECTOR
A4: AG | B4: REPUESTOS
A5: COBRANZA | B5: COBRANZAS
A6: FACTVENTRECGAS | B6: MAQUINAS
A7: FCANTREP | B7: REPUESTOS
A8: FCELIGA | B8: REPUESTOS
A9: FCELIGA_REFACT | B9: REPUESTOS
A10: FCEMIPYME-MAQ | B10: MAQUINAS
A11: FCEMIPYME-SER | B11: SERVICIOS
A12: FCEMIPYME_REP | B12: REPUESTOS
A13: FCEMIPYME_REP_REFAC | B13: REPUESTOS
A14: FCVTASERV | B14: SERVICIOS
... A35: VentaMaquinas | B35: MAQUINAS

Sheet CALCULOS
A1: COMPOSICION DE CUENTAS
L2: velocimetro
A3: CARTERA | B3: Suma de IMP. SECUNDARIO | D3: CARTERA | E3: IMPORTE | G3: CARTERA VENCIDA | H3: IMPORTE | K3: Etiquetas de fila
A4: VENCIDO<30 | B4: 53819.99 | D4: NO VENCIDO | E4: =IFERROR(VLOOKUP(D4,$A$4:$B$9,2,0),0) -> 229959.36 | G4: VENCIDO 30 | H4: =IFERROR(VLOOKUP(G4,$A$4:$B$10,2,0),0) -> 11729.98
A5: VENCIDO 60 | B5: 2414.99 | D5: VENCIDO 30 | E5: =IFERROR(VLOOKUP(D5,$A$4:$B$8,2,0),0) -> 11729.98 | G5: VENCIDO 60 | H5: =IFERROR(VLOOKUP(G5,$A$4:$B$10,2,0),0) -> 2414.99 | K5: VENCIDO>150 | L5: =IFERROR(VLOOKUP(K5,$D$3:$E$11,2,0),0) -> 900
A6: VENCIDO 90 | B6: 828 | D6: VENCIDO 60 | E6: =IFERROR(VLOOKUP(D6,$A$4:$B$8,2,0),0) -> 2414.99 | G6: VENCIDO 90 | H6: =IFERROR(VLOOKUP(G6,$A$4:$B$10,2,0),0) -> 828 | L6: =SUM(L4:L5) -> 900
A7: NO VENCIDO | B7: 229959.36 | D7: VENCIDO 90 | E7: =IFERROR(VLOOKUP(D7,$A$4:$B$8,2,0),0) -> 828 | G7: VENCIDO<30 | H7: =IFERROR(VLOOKUP(G7,$A$4:$B$10,2,0),0) -> 53819.99
A8: VENCIDO 30 | B8: 11729.98 | D8: VENCIDO<30 | E8: =IFERROR(VLOOKUP(D8,$A$4:$B$8,2,0),0) -> 53819.99 | G8: VENCIDO>150 | H8: =IFERROR(VLOOKUP(G8,$A$4:$B$10,2,0),0) -> 900
A9: VENCIDO>150 | B9: 900 | D9: VENCIDO>150 | E9: =IFERROR(VLOOKUP(D9,$A$4:$B$10,2,0),0) -> 900 | G9: Total general | H9: =+SUM(H4:H8) -> 69692.96
A10: Total general | B10: 299652.32 | D10: Total general | E10: =SUM(E4:E9) -> 299652.32
G11: %Cartera vencida | H11: =IFERROR(TEXT(H9/E10,"0,0%"),"-") -> 23,3%
A13: VENTAS VS CARTERA
A16: VENTA | B16: Suma de IMPORTE EN DÓLAR OFICIAL | D16: Etiquetas de fila | E16: Suma de IMP. SECUNDARIO | I16: MES | J16: VENTA | K16: CARTERA
A17: DIC-12 | B17: 5891.1561 | D17: ABR-04 | E17: 2414.99 | I17: OCT-10 | J17: =IFERROR(VLOOKUP(I17,$A$17:$B$21,2,0),0) -> 9937.1865 | K17: =IFERROR(+VLOOKUP(I17,$D$16:$E$21,2,FALSE),0) -> 0
A18: ENE-01 | B18: 257883.65 | D18: AGO-08 | E18: 113897.46 | I18: NOV-11 | J18: =IFERROR(VLOOKUP(I18,$A$17:$B$21,2,0),0) -> 7264.2974 | K18: =IFERROR(+VLOOKUP(I18,$D$16:$E$21,2,FALSE),0) -> 0
A19: FEB-02 | B19: 206733.3 | D19: ENE-01 | E19: 900 | I19: DIC-12 | J19: =IFERROR(VLOOKUP(I19,$A$17:$B$21,2,0),0) -> 5891.1561 | K19: =IFERROR(+VLOOKUP(I19,$D$16:$E$21,2,FALSE),0) -> 0
A20: NOV-11 | B20: 7264.2974 | D20: JUL-07 | E20: 36133.86 | I20: ENE-01 | J20: =IFERROR(VLOOKUP(I20,$A$17:$B$21,2,0),0) -> 257883.65 | K20: =IFERROR(+VLOOKUP(I20,$D$16:$E$21,2,FALSE),0) -> 900
A21: OCT-10 | B21: 9937.1865 | D21: JUN-06 | E21: 53819.99 | I21: FEB-02 | J21: =IFERROR(VLOOKUP(I21,$A$17:$B$21,2,0),0) -> 206733.3 | K21: =IFERROR(+VLOOKUP(I21,$D$16:$E$21,2,FALSE),0) -> 0
A22: Total general | B22: 487709.59 | D22: MAR-03 | E22: 828 | I22: MAR-03 | J22: =IFERROR(VLOOKUP(I22,$A$17:$B$21,2,0),0) -> 0 | K22: =IFERROR(+VLOOKUP(I22,$D$16:$E$21,2,FALSE),0) -> 0
D23: MAY-05 | E23: 11729.98 | J23: =IFERROR(VLOOKUP(I23,$A$17:$B$20,2,0),0) -> 0 | K23: =IFERROR(+VLOOKUP(I23,$D$16:$E$21,2,FALSE),0) -> 0
D24: SEPT-09 | E24: 79928.04 | J24: =IFERROR(VLOOKUP(I24,$A$17:$B$20,2,0),0) -> 0 | K24: =IFERROR(+VLOOKUP(I24,$D$16:$E$21,2,FALSE),0) -> 0
D25: Total general | E25: 299652.32 | J25: =IFERROR(VLOOKUP(I25,$A$17:$B$20,2,0),0) -> 0 | K25: =IFERROR(+VLOOKUP(I25,$D$16:$E$21,2,FALSE),0) -> 0
J26: =IFERROR(VLOOKUP(I26,$A$17:$B$20,2,0),0) -> 0 | K26: =IFERROR(+VLOOKUP(I26,$D$16:$E$21,2,FALSE),0) -> 0
J27: =IFERROR(VLOOKUP(I27,$A$17:$B$20,2,0),0) -> 0 | K27: =IFERROR(+VLOOKUP(I27,$D$16:$E$21,2,FALSE),0) -> 0
J28: =IFERROR(VLOOKUP(I28,$A$17:$B$20,2,0),0) -> 0 | K28: =IFERROR(+VLOOKUP(I28,$D$16:$E$21,2,FALSE),0) -> 0
I29: All | J29: =SUM(J17:J28) -> 487709.59 | K29: =SUM(K17:K28) -> 900
A31: ANILLOS CARTERA
A33: Etiquetas de fila | B33: Suma de IMP. SECUNDARIO | D33: DEUDORES | E33: Suma de IMP. PRINCIPAL | F33: DIFERENCIA
A34: NO VENCIDO | B34: 0.76742059 | D34: NO VENCIDO | E34: =IFERROR(VLOOKUP(D34,$A$33:$B$39,2,FALSE),0) -> 0.76742059 | F34: =1-E34 -> 0.23257941
A35: VENCIDO 30 | B35: 0.0391453 | D35: VENCIDO<30 | E35: =IFERROR(VLOOKUP(D35,$A$33:$B$39,2,FALSE),0) -> 0.17960812 | F35: =1-E35 -> 0.82039188
A36: VENCIDO 60 | B36: 0.0080593069 | D36: VENCIDO 30 | E36: =IFERROR(VLOOKUP(D36,$A$33:$B$39,2,FALSE),0) -> 0.0391453 | F36: =1-E36 -> 0.9608547
A37: VENCIDO 90 | B37: 0.0027632024 | D37: VENCIDO 60 | E37: =IFERROR(VLOOKUP(D37,$A$33:$B$39,2,FALSE),0) -> 0.0080593069 | F37: =1-E37 -> 0.99194069
A38: VENCIDO<30 | B38: 0.17960812 | D38: VENCIDO 90 | E38: =IFERROR(VLOOKUP(D38,$A$33:$B$39,2,FALSE),0) -> 0.0027632024 | F38: =1-E38 -> 0.9972368
A39: VENCIDO>150 | B39: 0.0030034808 | D39: VENCIDO>150 | E39: =IFERROR(VLOOKUP(D39,$A$33:$B$39,2,FALSE),0) -> 0.0030034808 | F39: =1-E39 -> 0.99699652
A40: Total general | B40: 1
D42: incobrables | E42: =+E39 -> 0.0030034808
A43: GRAFICO AREA
A45: Etiquetas de fila | B45: Suma de IMP. SECUNDARIO
A46: COBRANZAS | B46: 85219.04 | D46: SECTOR | E46: VALOR
A47: MAQUINAS | B47: 96900.97 | D47: COBRANZAS | E47: =IFERROR(+VLOOKUP(D47,$A$46:$B$49,2,0),0) -> 85219.04
A48: REPUESTOS | B48: 75252.52 | D48: REPUESTOS | E48: =IFERROR(+VLOOKUP(D48,$A$46:$B$49,2,0),0) -> 75252.52
A49: SERVICIOS | B49: 42279.79 | D49: SERVICIOS | E49: =IFERROR(+VLOOKUP(D49,$A$46:$B$49,2,0),0) -> 42279.79
A50: Total general | B50: 299652.32 | D50: MAQUINAS | E50: =IFERROR(+VLOOKUP(D50,$A$46:$B$49,2,0),0) -> 96900.97
D51: Total general | E51: =IFERROR(+VLOOKUP(D51,$A$46:$B$49,2,0),0) -> 0
A53: GRAFICO ZONAS
A56: Etiquetas de fila | B56: Suma de IMP. SECUNDARIO | D56: PROVINCIA | E56: SALDOS
A57: Catamarca | B57: 95940.44 | D57: Catamarca | E57: =+IFERROR(VLOOKUP(D57,$A$57:$B$66,2,FALSE),0) -> 95940.44
A58: Jujuy | B58: 86895.81 | D58: Jujuy | E58: =+IFERROR(VLOOKUP(D58,$A$57:$B$66,2,FALSE),0) -> 86895.81
A59: Salta | B59: 19308.47 | D59: Salta | E59: =+IFERROR(VLOOKUP(D59,$A$57:$B$66,2,FALSE),0) -> 19308.47
A60: Santiago del Estero | B60: 41391.86 | D60: Santiago del Estero | E60: =+IFERROR(VLOOKUP(D60,$A$57:$B$66,2,FALSE),0) -> 41391.86
A61: Tucuman | B61: 56115.74 | D61: Tucuman | E61: =+IFERROR(VLOOKUP(D61,$A$57:$B$66,2,FALSE),0) -> 56115.74
A62: Total general | B62: 299652.32 | E62: =+IFERROR(VLOOKUP(D62,$A$57:$B$66,2,FALSE),0) -> 0
E63: =+IFERROR(VLOOKUP(D63,$A$57:$B$66,2,FALSE),0) -> 0
E64: =+IFERROR(VLOOKUP(D64,$A$57:$B$66,2,FALSE),0) -> 0
E65: =+IFERROR(VLOOKUP(D65,$A$57:$B$66,2,FALSE),0) -> 0
D66: Total general
A69: VELOCIMETRO
A71: Cartera | B71: =+E51 -> 0
A72: incobrables | B72: =+L6 -> 900 | D72: Criterio | E72: Diferencia | F72: Meta | I72: Criterio | J72: Diferencia | K72: Meta
B73: =+E42 -> 0.0030034808 | D73: POSITIVO | E73: 0.3 | F73: 0.3 | I73: POSITIVO | J73: 0.01 | K73: 0
D74: ACEPTABLE | E74: 0.3 | F74: 0.5 | I74: ACEPTABLE | J74: 0.005 | K74: 0.01
D75: NEGATIVO | E75: 0.2 | F75: 0.8 | I75: NEGATIVO | J75: 0.005 | K75: 0.015
B76: =+IF(B73<0.5%,"Gestion Sana", "Revisar Mora") -> Gestion Sana | E76: =SUM(E73:E75) -> 0.8 | J76: =SUM(J73:J75) -> 0.02 | K76: 0.02
E77: x | F77: y | J77: x | K77: y
A78: Cartera | B78: =+E9 -> 900 | D78: Base | E78: 0 | F78: 0 | I78: Base | J78: 0 | K78: 0
A79: Ventas | B79: =+J29 -> 487709.59 | D79: Puntero | E79: =IF(B80>E76,-COS(PI()*E76/E76),-COS(PI()*B80/E76)) -> -0.99997374 | F79: =IF(B80>E76,+SIN(PI()*E76/E76),+SIN(PI()*B80/E76)) -> 0.0072466503 | I79: Puntero | J79: =-COS(PI() * (B73 / 2%)) -> -0.89075816 | K79: =SIN(PI()*B73/2%) -> 0.45447761
A80: Indicador | B80: =+B78/B79 -> 0.0018453605
E82: 1
E83: 1
A84: ="CORTE: " & TEXT(DATE(2026,6,30),"DD/MM/YYYY") -> CORTE: 30/06/2026
B87: {=SUMPRODUCT((COMPOSICIONSALDOneo[DIAS DE MORA]>0)*COMPOSICIONSALDOneo[DIAS DE MORA]*COMPOSICIONSALDOneo[IMP. SECUNDARIO])/SUMIF(COMPOSICIONSALDOneo[DIAS DE MORA],">0",COMPOSICIONSALDOneo[IMP. SECUNDARIO])} -> 21.576258
G92: RANKING DEUDA
B94: CLIENTES | C94: Suma de IMP. SECUNDARIO | G94: RANKING DEUDORES | H94: ESTADO DE DEUDA
B95: Cliente 52 | C95: 41229.61 | G95: CLIENTES | H95: VENCIDO<30 | I95: NO VENCIDO | J95: VENCIDO 60 | K95: VENCIDO 90 | L95: VENCIDO 30 | M95: VENCIDO>150 | N95: Total general | P95: =COUNTA(R95:R274)-COUNTIF(R95:R200,"*Total*") -> 51 | R95: =IFERROR(IF(OR($B95="",ISNUMBER(SEARCH("Total",$B95))),"",$B95),"") -> Cliente 52 | S95: =IFERROR(IF($R95="","",$C95),"") -> 41229.61 | U95: =IFERROR(OFFSET($R$94,$P$96+ROW()-95,0),"") -> Cliente 7 | V95: =IFERROR(OFFSET($S$94,$P$96+ROW()-95,0),"") -> 8140.58
B96: Cliente 34 | C96: 18767.63 | G96: Cliente 46 | K96: 36.14 | N96: 36.14 | P96: 17 | R96: =IFERROR(IF(OR($B96="",ISNUMBER(SEARCH("Total",$B96))),"",$B96),"") -> Cliente 34 | S96: =IFERROR(IF($R96="","",$C96),"") -> 18767.63 | U96: =IFERROR(OFFSET($R$94,$P$96+ROW()-95,0),"") -> Cliente 20 | V96: =IFERROR(OFFSET($S$94,$P$96+ROW()-95,0),"") -> 8097.48
B97: Cliente 17 | C97: 17635.29 | G97: Cliente 4 | J97: 128.89 | N97: 128.89 | R97: =IFERROR(IF(OR($B97="",ISNUMBER(SEARCH("Total",$B97))),"",$B97),"") -> Cliente 17 | S97: =IFERROR(IF($R97="","",$C97),"") -> 17635.29 | U97: =IFERROR(OFFSET($R$94,$P$96+ROW()-95,0),"") -> Cliente 59 | V97: =IFERROR(OFFSET($S$94,$P$96+ROW()-95,0),"") -> 5103.09
B98: Cliente 11 | C98: 17368.37 | G98: Cliente 44 | K98: 156.47 | N98: 156.47 | R98: =IFERROR(IF(OR($B98="",ISNUMBER(SEARCH("Total",$B98))),"",$B98),"") -> Cliente 11 | S98: =IFERROR(IF($R98="","",$C98),"") -> 17368.37 | U98: =IFERROR(OFFSET($R$94,$P$96+ROW()-95,0),"") -> Cliente 30 | V98: =IFERROR(OFFSET($S$94,$P$96+ROW()-95,0),"") -> 4707.75
B99: Cliente 2 | C99: 17045.83 | G99: Cliente 5 | K99: 161.27 | N99: 161.27 | R99: =IFERROR(IF(OR($B99="",ISNUMBER(SEARCH("Total",$B99))),"",$B99),"") -> Cliente 2 | S99: =IFERROR(IF($R99="","",$C99),"") -> 17045.83 | U99: =IFERROR(OFFSET($R$94,$P$96+ROW()-95,0),"") -> Cliente 25 | V99: =IFERROR(OFFSET($S$94,$P$96+ROW()-95,0),"") -> 3228.85
B100: Cliente 35 | C100: 16485.99 | G100: Cliente 47 | M100: 195.66 | N100: 195.66 | R100: =IFERROR(IF(OR($B100="",ISNUMBER(SEARCH("Total",$B100))),"",$B100),"") -> Cliente 35 | S100: =IFERROR(IF($R100="","",$C100),"") -> 16485.99 | U100: =IFERROR(OFFSET($R$94,$P$96+ROW()-95,0),"") -> Cliente 42 | V100: =IFERROR(OFFSET($S$94,$P$96+ROW()-95,0),"") -> 2917.47
B101: Cliente 27 | C101: 16391 | G101: Cliente 32 | L101: 206.18 | N101: 206.18 | R101: =IFERROR(IF(OR($B101="",ISNUMBER(SEARCH("Total",$B101))),"",$B101),"") -> Cliente 27 | S101: =IFERROR(IF($R101="","",$C101),"") -> 16391 | U101: =IFERROR(OFFSET($R$94,$P$96+ROW()-95,0),"") -> Cliente 31 | V101: =IFERROR(OFFSET($S$94,$P$96+ROW()-95,0),"") -> 2764.02
B102: Cliente 22 | C102: 15497.39 | G102: Cliente 57 | J102: 415.31 | K102: 150.59 | N102: 565.9 | R102: =IFERROR(IF(OR($B102="",ISNUMBER(SEARCH("Total",$B102))),"",$B102),"") -> Cliente 22 | S102: =IFERROR(IF($R102="","",$C102),"") -> 15497.39 | U102: =IFERROR(OFFSET($R$94,$P$96+ROW()-95,0),"") -> Cliente 18 | V102: =IFERROR(OFFSET($S$94,$P$96+ROW()-95,0),"") -> 1868.67
B103: Cliente 53 | C103: 15453.74 | G103: Cliente 23 | J103: 365.01 | M103: 340.81 | N103: 705.82 | R103: =IFERROR(IF(OR($B103="",ISNUMBER(SEARCH("Total",$B103))),"",$B103),"") -> Cliente 53 | S103: =IFERROR(IF($R103="","",$C103),"") -> 15453.74 | U103: =IFERROR(OFFSET($R$94,$P$96+ROW()-95,0),"") -> Cliente 13 | V103: =IFERROR(OFFSET($S$94,$P$96+ROW()-95,0),"") -> 1713.03
B104: Cliente 36 | C104: 15391.48 | G104: Cliente 60 | L104: 975.71 | N104: 975.71 | R104: =IFERROR(IF(OR($B104="",ISNUMBER(SEARCH("Total",$B104))),"",$B104),"") -> Cliente 36 | S104: =IFERROR(IF($R104="","",$C104),"") -> 15391.48 | U104: =IFERROR(OFFSET($R$94,$P$96+ROW()-95,0),"") -> Cliente 55 | V104: =IFERROR(OFFSET($S$94,$P$96+ROW()-95,0),"") -> 1574.21
B105: Cliente 41 | C105: 15330.03 | G105: Cliente 58 | K105: 164.54 | L105: 1095.9 | N105: 1260.44 | R105: =IFERROR(IF(OR($B105="",ISNUMBER(SEARCH("Total",$B105))),"",$B105),"") -> Cliente 41 | S105: =IFERROR(IF($R105="","",$C105),"") -> 15330.03
B106: Cliente 54 | C106: 10951.14 | G106: Cliente 55 | L106: 1574.21 | N106: 1574.21 | R106: =IFERROR(IF(OR($B106="",ISNUMBER(SEARCH("Total",$B106))),"",$B106),"") -> Cliente 54 | S106: =IFERROR(IF($R106="","",$C106),"") -> 10951.14
B107: Cliente 38 | C107: 9924.24 | G107: Cliente 13 | L107: 1713.03 | N107: 1713.03 | R107: =IFERROR(IF(OR($B107="",ISNUMBER(SEARCH("Total",$B107))),"",$B107),"") -> Cliente 38 | S107: =IFERROR(IF($R107="","",$C107),"") -> 9924.24
B108: Cliente 19 | C108: 9771.06 | G108: Cliente 18 | J108: 378.82 | L108: 1489.85 | N108: 1868.67 | R108: =IFERROR(IF(OR($B108="",ISNUMBER(SEARCH("Total",$B108))),"",$B108),"") -> Cliente 19 | S108: =IFERROR(IF($R108="","",$C108),"") -> 9771.06
B109: Cliente 51 | C109: 9220.3 | G109: Cliente 31 | H109: 2274.17 | L109: 489.85 | N109: 2764.02 | R109: =IFERROR(IF(OR($B109="",ISNUMBER(SEARCH("Total",$B109))),"",$B109),"") -> Cliente 51 | S109: =IFERROR(IF($R109="","",$C109),"") -> 9220.3
B110: Cliente 15 | C110: 8681.59 | G110: Cliente 42 | I110: 2758.48 | K110: 158.99 | N110: 2917.47 | R110: =IFERROR(IF(OR($B110="",ISNUMBER(SEARCH("Total",$B110))),"",$B110),"") -> Cliente 15 | S110: =IFERROR(IF($R110="","",$C110),"") -> 8681.59
B111: Cliente 7 | C111: 8140.58 | G111: Cliente 25 | I111: 3228.85 | N111: 3228.85 | R111: =IFERROR(IF(OR($B111="",ISNUMBER(SEARCH("Total",$B111))),"",$B111),"") -> Cliente 7 | S111: =IFERROR(IF($R111="","",$C111),"") -> 8140.58
B112: Cliente 20 | C112: 8097.48 | G112: Cliente 30 | H112: 4707.75 | N112: 4707.75 | R112: =IFERROR(IF(OR($B112="",ISNUMBER(SEARCH("Total",$B112))),"",$B112),"") -> Cliente 20 | S112: =IFERROR(IF($R112="","",$C112),"") -> 8097.48
B113: Cliente 59 | C113: 5103.09 | G113: Cliente 59 | H113: 5103.09 | N113: 5103.09 | R113: =IFERROR(IF(OR($B113="",ISNUMBER(SEARCH("Total",$B113))),"",$B113),"") -> Cliente 59 | S113: =IFERROR(IF($R113="","",$C113),"") -> 5103.09
B114: Cliente 30 | C114: 4707.75 | G114: Cliente 20 | H114: 7733.95 | M114: 363.53 | N114: 8097.48 | R114: =IFERROR(IF(OR($B114="",ISNUMBER(SEARCH("Total",$B114))),"",$B114),"") -> Cliente 30 | S114: =IFERROR(IF($R114="","",$C114),"") -> 4707.75
B115: Cliente 25 | C115: 3228.85 | G115: Cliente 7 | H115: 6258.53 | I115: 1882.05 | N115: 8140.58 | R115: =IFERROR(IF(OR($B115="",ISNUMBER(SEARCH("Total",$B115))),"",$B115),"") -> Cliente 25 | S115: =IFERROR(IF($R115="","",$C115),"") -> 3228.85
B116: Cliente 42 | C116: 2917.47 | G116: Cliente 15 | I116: 8681.59 | N116: 8681.59 | R116: =IFERROR(IF(OR($B116="",ISNUMBER(SEARCH("Total",$B116))),"",$B116),"") -> Cliente 42 | S116: =IFERROR(IF($R116="","",$C116),"") -> 2917.47
B117: Cliente 31 | C117: 2764.02 | G117: Cliente 51 | H117: 8974.51 | J117: 245.79 | N117: 9220.3 | R117: =IFERROR(IF(OR($B117="",ISNUMBER(SEARCH("Total",$B117))),"",$B117),"") -> Cliente 31 | S117: =IFERROR(IF($R117="","",$C117),"") -> 2764.02
B118: Cliente 18 | C118: 1868.67 | G118: Cliente 19 | H118: 8639.1 | I118: 1131.96 | N118: 9771.06 | R118: =IFERROR(IF(OR($B118="",ISNUMBER(SEARCH("Total",$B118))),"",$B118),"") -> Cliente 18 | S118: =IFERROR(IF($R118="","",$C118),"") -> 1868.67
B119: Cliente 13 | C119: 1713.03 | G119: Cliente 38 | I119: 9924.24 | N119: 9924.24 | R119: =IFERROR(IF(OR($B119="",ISNUMBER(SEARCH("Total",$B119))),"",$B119),"") -> Cliente 13 | S119: =IFERROR(IF($R119="","",$C119),"") -> 1713.03
B120: Cliente 55 | C120: 1574.21 | G120: Cliente 54 | I120: 10951.14 | N120: 10951.14 | R120: =IFERROR(IF(OR($B120="",ISNUMBER(SEARCH("Total",$B120))),"",$B120),"") -> Cliente 55 | S120: =IFERROR(IF($R120="","",$C120),"") -> 1574.21
B121: Cliente 58 | C121: 1260.44 | G121: Cliente 41 | I121: 15330.03 | N121: 15330.03 | R121: =IFERROR(IF(OR($B121="",ISNUMBER(SEARCH("Total",$B121))),"",$B121),"") -> Cliente 58 | S121: =IFERROR(IF($R121="","",$C121),"") -> 1260.44
...

Sheet Base nueva
A1: =+TODAY() -> 46206
A2: Documento tipo | B2: FECHA COMPROBANTE | C2: CLIENTE | D2: COMPROBANTE | E2: DESCRIPCION | F2: MONEDA | G2: IMP. TRANSACCION | H2: COTIZACION | I2: IMP. PRINCIPAL | J2: IMP. SECUNDARIO | K2: FECHA VTO. | L2: DIAS DE MORA | M2: FECH | N2: MES2 | O2: MES | P2: ESTADO SEGÚN MORA | Q2: ESTADO | R2: AREA | S2: PROVINCIA | T2: ALERTA VENC.
A3: NCMAN | B3: 46239 | C3: Cliente 2 | D3: FC-1001 | E3: Facturacion mensual | F3: Dólar Divisa | G3: 4611.79 | H3: 1 | I3: 4611.79 | J3: 4611.79 | K3: 46259 | L3: =IF(COMPOSICIONSALDOneo[[#This Row],[IMP. PRINCIPAL]] > 0, MAX(0, $A$1-COMPOSICIONSALDOneo[[#This Row],[FECHA VTO.]]), 0) -> 0 | M3: =UPPER(TEXT(COMPOSICIONSALDOneo[[#This Row],[FECHA VTO.]],"MMM")) -> AGO | N3: =TEXT(MONTH(COMPOSICIONSALDOneo[[#This Row],[FECHA VTO.]]),"00") -> 08 | O3: =+CONCATENATE(COMPOSICIONSALDOneo[[#This Row],[FECH]],"-",COMPOSICIONSALDOneo[[#This Row],[MES2]]) -> AGO-08 | P3: =IF(L3=0,"NO VENCIDO",IF(L3<30,"VENCIDO<30",IF(L3<60,"VENCIDO 30",IF(L3<90,"VENCIDO 60",IF(L3<150,"VENCIDO 90","VENCIDO>150"))))) -> NO VENCIDO | Q3: =IF(COMPOSICIONSALDOneo[[#This Row],[DIAS DE MORA]]<1,"NO VENCIDO",IF(COMPOSICIONSALDOneo[[#This Row],[DIAS DE MORA]]>=1,"VENCIDO","INCOBRABLE")) -> NO VENCIDO | R3: =+VLOOKUP(COMPOSICIONSALDOneo[[#This Row],[Documento tipo]],Tabla7[#All],2,0) -> COBRANZAS | S3: =+VLOOKUP(COMPOSICIONSALDOneo[[#This Row],[CLIENTE]],Tabla5[],3,FALSE) -> Santiago del Estero | T3: =IF(COMPOSICIONSALDOneo[[#This Row],[IMP. PRINCIPAL]]<0, "No vencido", IF(AND(COMPOSICIONSALDOneo[[#This Row],[FECHA VTO.]]-TODAY()>=1, COMPOSICIONSALDOneo[[#This Row],[FECHA VTO.]]-TODAY()<=5), "Vence 2-5 días", IF(COMPOSICIONSALDOneo[[#This Row],[FECHA VTO.]]-TODAY()<0, "Vencido", "No vencido"))) -> No vencido
A4: NCCEMIPYME-REP | B4: 46011 | C4: Cliente 23 | D4: FC-1002 | E4: Insumos varios | F4: Dólares | G4: 192.17 | H4: 1 | I4: 192.17 | J4: 192.17 | K4: 46044 | L4: =IF(COMPOSICIONSALDOneo[[#This Row],[IMP. PRINCIPAL]] > 0, MAX(0, $A$1-COMPOSICIONSALDOneo[[#This Row],[FECHA VTO.]]), 0) -> 162 | M4: =UPPER(TEXT(COMPOSICIONSALDOneo[[#This Row],[FECHA VTO.]],"MMM")) -> ENE | N4: =TEXT(MONTH(COMPOSICIONSALDOneo[[#This Row],[FECHA VTO.]]),"00") -> 01 | O4: =+CONCATENATE(COMPOSICIONSALDOneo[[#This Row],[FECH]],"-",COMPOSICIONSALDOneo[[#This Row],[MES2]]) -> ENE-01 | P4: =IF(L4=0,"NO VENCIDO",IF(L4<30,"VENCIDO<30",IF(L4<60,"VENCIDO 30",IF(L4<90,"VENCIDO 60",IF(L4<150,"VENCIDO 90","VENCIDO>150"))))) -> VENCIDO>150 | Q4: =IF(COMPOSICIONSALDOneo[[#This Row],[DIAS DE MORA]]<1,"NO VENCIDO",IF(COMPOSICIONSALDOneo[[#This Row],[DIAS DE MORA]]>=1,"VENCIDO","INCOBRABLE")) -> VENCIDO | R4: =+VLOOKUP(COMPOSICIONSALDOneo[[#This Row],[Documento tipo]],Tabla7[#All],2,0) -> REPUESTOS | S4: =+VLOOKUP(COMPOSICIONSALDOneo[[#This Row],[CLIENTE]],Tabla5[],3,FALSE) -> Tucuman | T4: =IF(COMPOSICIONSALDOneo[[#This Row],[IMP. PRINCIPAL]]<0, "No vencido", IF(AND(COMPOSICIONSALDOneo[[#This Row],[FECHA VTO.]]-TODAY()>=1, COMPOSICIONSALDOneo[[#This Row],[FECHA VTO.]]-TODAY()<=5), "Vence 2-5 días", IF(COMPOSICIONSALDOneo[[#This Row],[FECHA VTO.]]-TODAY()<0, "Vencido", "No vencido"))) -> Vencido
A5: NDVI | B5: 46197 | C5: Cliente 15 | D5: FC-1003 | E5: Facturacion mensual | F5: Pesos | G5: 8681.59 | H5: 1095.1 | I5: 8681.59 | J5: 8681.59 | K5: 46234 | L5: =IF(COMPOSICIONSALDOneo[[#This Row],[IMP. PRINCIPAL]] > 0, MAX(0, $A$1-COMPOSICIONSALDOneo[[#This Row],[FECHA VTO.]]), 0) -> 0 | M5: =UPPER(TEXT(COMPOSICIONSALDOneo[[#This Row],[FECHA VTO.]],"MMM")) -> JUL | N5: =TEXT(MONTH(COMPOSICIONSALDOneo[[#This Row],[FECHA VTO.]]),"00") -> 07 | O5: =+CONCATENATE(COMPOSICIONSALDOneo[[#This Row],[FECH]],"-",COMPOSICIONSALDOneo[[#This Row],[MES2]]) -> JUL-07 | P5: =IF(L5=0,"NO VENCIDO",IF(L5<30,"VENCIDO<30",IF(L5<60,"VENCIDO 30",IF(L5<90,"VENCIDO 60",IF(L5<150,"VENCIDO 90","VENCIDO>150"))))) -> NO VENCIDO | Q5: =IF(COMPOSICIONSALDOneo[[#This Row],[DIAS DE MORA]]<1,"NO VENCIDO",IF(COMPOSICIONSALDOneo[[#This Row],[DIAS DE MORA]]>=1,"VENCIDO","INCOBRABLE")) -> NO VENCIDO | R5: =+VLOOKUP(COMPOSICIONSALDOneo[[#This Row],[Documento tipo]],Tabla7[#All],2,0) -> COBRANZAS | S5: =+VLOOKUP(COMPOSICIONSALDOneo[[#This Row],[CLIENTE]],Tabla5[],3,FALSE) -> Tucuman | T5: =IF(COMPOSICIONSALDOneo[[#This Row],[IMP. PRINCIPAL]]<0, "No vencido", IF(AND(COMPOSICIONSALDOneo[[#This Row],[FECHA VTO.]]-TODAY()>=1, COMPOSICIONSALDOneo[[#This Row],[FECHA VTO.]]-TODAY()<=5), "Vence 2-5 días", IF(COMPOSICIONSALDOneo[[#This Row],[FECHA VTO.]]-TODAY()<0, "Vencido", "No vencido"))) -> No vencido
A6: NCMAN | B6: 46118 | C6: Cliente 57 | D6: FC-1004 | E6: Mantenimiento | F6: Dólares | G6: 415.31 | H6: 1 | I6: 415.31 | J6: 415.31 | K6: 46133 | L6: =IF(COMPOSICIONSALDOneo[[#This Row],[IMP. PRINCIPAL]] > 0, MAX(0, $A$1-COMPOSICIONSALDOneo[[#This Row],[FECHA VTO.]]), 0) -> 73 | M6: =UPPER(TEXT(COMPOSICIONSALDOneo[[#This Row],[FECHA VTO.]],"MMM")) -> ABR | N6: =TEXT(MONTH(COMPOSICIONSALDOneo[[#This Row],[FECHA VTO.]]),"00") -> 04 | O6: =+CONCATENATE(COMPOSICIONSALDOneo[[#This Row],[FECH]],"-",COMPOSICIONSALDOneo[[#This Row],[MES2]]) -> ABR-04 | P6: =IF(L6=0,"NO VENCIDO",IF(L6<30,"VENCIDO<30",IF(L6<60,"VENCIDO 30",IF(L6<90,"VENCIDO 60",IF(L6<150,"VENCIDO 90","VENCIDO>150"))))) -> VENCIDO 60 | Q6: =IF(COMPOSICIONSALDOneo[[#This Row],[DIAS DE MORA]]<1,"NO VENCIDO",IF(COMPOSICIONSALDOneo[[#This Row],[DIAS DE MORA]]>=1,"VENCIDO","INCOBRABLE")) -> VENCIDO | R6: =+VLOOKUP(COMPOSICIONSALDOneo[[#This Row],[Documento tipo]],Tabla7[#All],2,0) -> COBRANZAS | S6: =+VLOOKUP(COMPOSICIONSALDOneo[[#This Row],[CLIENTE]],Tabla5[],3,FALSE) -> Catamarca | T6: =IF(COMPOSICIONSALDOneo[[#This Row],[IMP. PRINCIPAL]]<0, "No vencido", IF(AND(COMPOSICIONSALDOneo[[#This Row],[FECHA VTO.]]-TODAY()>=1, COMPOSICIONSALDOneo[[#This Row],[FECHA VTO.]]-TODAY()<=5), "Vence 2-5 días", IF(COMPOSICIONSALDOneo[[#This Row],[FECHA VTO.]]-TODAY()<0, "Vencido", "No vencido"))) -> Vencido
A7: AG | B7: 46031 | C7: Cliente 23 | D7: FC-1005 | F7: Dólar Divisa | G7: 148.64 | H7: 1 | I7: 148.64 | J7: 148.64 | K7: 46050 | L7: =IF(COMPOSICIONSALDOneo[[#This Row],[IMP. PRINCIPAL]] > 0, MAX(0, $A$1-COMPOSICIONSALDOneo[[#This Row],[FECHA VTO.]]), 0) -> 156 | M7: =UPPER(TEXT(COMPOSICIONSALDOneo[[#This Row],[FECHA VTO.]],"MMM")) -> ENE | N7: =TEXT(MONTH(COMPOSICIONSALDOneo[[#This Row],[FECHA VTO.]]),"00") -> 01 | O7: =+CONCATENATE(COMPOSICIONSALDOneo[[#This Row],[FECH]],"-",COMPOSICIONSALDOneo[[#This Row],[MES2]]) -> ENE-01 | P7: =IF(L7=0,"NO VENCIDO",IF(L7<30,"VENCIDO<30",IF(L7<60,"VENCIDO 30",IF(L7<90,"VENCIDO 60",IF(L7<150,"VENCIDO 90","VENCIDO>150"))))) -> VENCIDO>150 | Q7: =IF(COMPOSICIONSALDOneo[[#This Row],[DIAS DE MORA]]<1,"NO VENCIDO",IF(COMPOSICIONSALDOneo[[#This Row],[DIAS DE MORA]]>=1,"VENCIDO","INCOBRABLE")) -> VENCIDO | R7: =+VLOOKUP(COMPOSICIONSALDOneo[[#This Row],[Documento tipo]],Tabla7[#All],2,0) -> REPUESTOS | S7: =+VLOOKUP(COMPOSICIONSALDOneo[[#This Row],[CLIENTE]],Tabla5[],3,FALSE) -> Tucuman | T7: =IF(COMPOSICIONSALDOneo[[#This Row],[IMP. PRINCIPAL]]<0, "No vencido", IF(AND(COMPOSICIONSALDOneo[[#This Row],[FECHA VTO.]]-TODAY()>=1, COMPOSICIONSALDOneo[[#This Row],[FECHA VTO.]]-TODAY()<=5), "Vence 2-5 días", IF(COMPOSICIONSALDOneo[[#This Row],[FECHA VTO.]]-TODAY()<0, "Vencido", "No vencido"))) -> Vencido
A8: NDCDVM | B8: 46240 | C8: Cliente 38 | D8: FC-1006 | E8: OT reparacion | F8: Dólar Divisa | G8: 9924.24 | H8: 1 | I8: 9924.24 | J8: 9924.24 | K8: 46259 | L8: =IF(COMPOSICIONSALDOneo[[#This Row],[IMP. PRINCIPAL]] > 0, MAX(0, $A$1-COMPOSICIONSALDOneo[[#This Row],[FECHA VTO.]]), 0) -> 0 | M8: =UPPER(TEXT(COMPOSICIONSALDOneo[[#This Row],[FECHA VTO.]],"MMM")) -> AGO | N8: =TEXT(MONTH(COMPOSICIONSALDOneo[[#This Row],[FECHA VTO.]]),"00") -> 08 | O8: =+CONCATENATE(COMPOSICIONSALDOneo[[#This Row],[FECH]],"-",COMPOSICIONSALDOneo[[#This Row],[MES2]]) -> AGO-08 | P8: =IF(L8=0,"NO VENCIDO",IF(L8<30,"VENCIDO<30",IF(L8<60,"VENCIDO 30",IF(L8<90,"VENCIDO 60",IF(L8<150,"VENCIDO 90","VENCIDO>150"))))) -> NO VENCIDO | Q8: =IF(COMPOSICIONSALDOneo[[#This Row],[DIAS DE MORA]]<1,"NO VENCIDO",IF(COMPOSICIONSALDOneo[[#This Row],[DIAS DE MORA]]>=1,"VENCIDO","INCOBRABLE")) -> NO VENCIDO | R8: =+VLOOKUP(COMPOSICIONSALDOneo[[#This Row],[Documento tipo]],Tabla7[#All],2,0) -> MAQUINAS | S8: =+VLOOKUP(COMPOSICIONSALDOneo[[#This Row],[CLIENTE]],Tabla5[],3,FALSE) -> Catamarca | T8: =IF(COMPOSICIONSALDOneo[[#This Row],[IMP. PRINCIPAL]]<0, "No vencido", IF(AND(COMPOSICIONSALDOneo[[#This Row],[FECHA VTO.]]-TODAY()>=1, COMPOSICIONSALDOneo[[#This Row],[FECHA VTO.]]-TODAY()<=5), "Vence 2-5 días", IF(COMPOSICIONSALDOneo[[#This Row],[FECHA VTO.]]-TODAY()<0, "Vencido", "No vencido"))) -> No vencido
A9: FCELIGA_REFACT | B9: 46095 | C9: Cliente 44 | D9: FC-1007 | E9: Facturacion mensual | F9: Pesos | G9: 156.47 | H9: 1012.3 | I9: 156.47 | J9: 156.47 | K9: 46110 | L9: =IF(COMPOSICIONSALDOneo[[#This Row],[IMP. PRINCIPAL]] > 0, MAX(0, $A$1-COMPOSICIONSALDOneo[[#This Row],[FECHA VTO.]]), 0) -> 96 | M9: =UPPER(TEXT(COMPOSICIONSALDOneo[[#This Row],[FECHA VTO.]],"MMM")) -> MAR | N9: =TEXT(MONTH(COMPOSICIONSALDOneo[[#This Row],[FECHA VTO.]]),"00") -> 03 | O9: =+CONCATENATE(COMPOSICIONSALDOneo[[#This Row],[FECH]],"-",COMPOSICIONSALDOneo[[#This Row],[MES2]]) -> MAR-03 | P9: =IF(L9=0,"NO VENCIDO",IF(L9<30,"VENCIDO<30",IF(L9<60,"VENCIDO 30",IF(L9<90,"VENCIDO 60",IF(L9<150,"VENCIDO 90","VENCIDO>150"))))) -> VENCIDO 90 | Q9: =IF(COMPOSICIONSALDOneo[[#This Row],[DIAS DE MORA]]<1,"NO VENCIDO",IF(COMPOSICIONSALDOneo[[#This Row],[DIAS DE MORA]]>=1,"VENCIDO","INCOBRABLE")) -> VENCIDO | R9: =+VLOOKUP(COMPOSICIONSALDOneo[[#This Row],[Documento tipo]],Tabla7[#All],2,0) -> REPUESTOS | S9: =+VLOOKUP(COMPOSICIONSALDOneo[[#This Row],[CLIENTE]],Tabla5[],3,FALSE) -> Santiago del Estero | T9: =IF(COMPOSICIONSALDOneo[[#This Row],[IMP. PRINCIPAL]]<0, "No vencido", IF(AND(COMPOSICIONSALDOneo[[#This Row],[FECHA VTO.]]-TODAY()>=1, COMPOSICIONSALDOneo[[#This Row],[FECHA VTO.]]-TODAY()<=5), "Vence 2-5 días", IF(COMPOSICIONSALDOneo[[#This Row],[FECHA VTO.]]-TODAY()<0, "Vencido", "No vencido"))) -> Vencido
A10: FCEMIPYME_REP_REFAC | B10: 46254 | C10: Cliente 35 | D10: FC-1008 | E10: Venta repuestos | F10: Pesos | G10: 16014.59 | H10: 1030.26 | I10: 16014.59 | J10: 16014.59 | K10: 46271 | L10: =IF(COMPOSICIONSALDOneo[[#This Row],[IMP. PRINCIPAL]] > 0, MAX(0, $A$1-COMPOSICIONSALDOneo[[#This Row],[FECHA VTO.]]), 0) -> 0 | M10: =UPPER(TEXT(COMPOSICIONSALDOneo[[#This Row],[FECHA VTO.]],"MMM")) -> SEPT | N10: =TEXT(MONTH(COMPOSICIONSALDOneo[[#This Row],[FECHA VTO.]]),"00") -> 09 | O10: =+CONCATENATE(COMPOSICIONSALDOneo[[#This Row],[FECH]],"-",COMPOSICIONSALDOneo[[#This Row],[MES2]]) -> SEPT-09 | P10: =IF(L10=0,"NO VENCIDO",IF(L10<30,"VENCIDO<30",IF(L10<60,"VENCIDO 30",IF(L10<90,"VENCIDO 60",IF(L10<150,"VENCIDO 90","VENCIDO>150"))))) -> NO VENCIDO | Q10: =IF(COMPOSICIONSALDOneo[[#This Row],[DIAS DE MORA]]<1,"NO VENCIDO",IF(COMPOSICIONSALDOneo[[#This Row],[DIAS DE MORA]]>=1,"VENCIDO","INCOBRABLE")) -> NO VENCIDO | R10: =+VLOOKUP(COMPOSICIONSALDOneo[[#This Row],[Documento tipo]],Tabla7[#All],2,0) -> REPUESTOS | S10: =+VLOOKUP(COMPOSICIONSALDOneo[[#This Row],[CLIENTE]],Tabla5[],3,FALSE) -> Santiago del Estero | T10: =IF(COMPOSICIONSALDOneo[[#This Row],[IMP. PRINCIPAL]]<0, "No vencido", IF(AND(COMPOSICIONSALDOneo[[#This Row],[FECHA VTO.]]-TODAY()>=1, COMPOSICIONSALDOneo[[#This Row],[FECHA VTO.]]-TODAY()<=5), "Vence 2-5 días", IF(COMPOSICIONSALDOneo[[#This Row],[FECHA VTO.]]-TODAY()<0, "Vencido", "No vencido"))) -> No vencido
A11: NCCEMIPYME-SER | B11: 46168 | C11: Cliente 19 | D11: FC-1009 | E11: Service programado | F11: Dólares | G11: 8639.1 | H11: 1 | I11: 8639.1 | J11: 8639.1 | K11: 46196 | L11: =IF(COMPOSICIONSALDOneo[[#This Row],[IMP. PRINCIPAL]] > 0, MAX(0, $A$1-COMPOSICIONSALDOneo[[#This Row],[FECHA VTO.]]), 0) -> 10 | M11: =UPPER(TEXT(COMPOSICIONSALDOneo[[#This Row],[FECHA VTO.]],"MMM")) -> JUN | N11: =TEXT(MONTH(COMPOSICIONSALDOneo[[#This Row],[FECHA VTO.]]),"00") -> 06 | O11: =+CONCATENATE(COMPOSICIONSALDOneo[[#This Row],[FECH]],"-",COMPOSICIONSALDOneo[[#This Row],[MES2]]) -> JUN-06 | P11: =IF(L11=0,"NO VENCIDO",IF(L11<30,"VENCIDO<30",IF(L11<60,"VENCIDO 30",IF(L11<90,"VENCIDO 60",IF(L11<150,"VENCIDO 90","VENCIDO>150"))))) -> VENCIDO<30 | Q11: =IF(COMPOSICIONSALDOneo[[#This Row],[DIAS DE MORA]]<1,"NO VENCIDO",IF(COMPOSICIONSALDOneo[[#This Row],[DIAS DE MORA]]>=1,"VENCIDO","INCOBRABLE")) -> VENCIDO | R11: =+VLOOKUP(COMPOSICIONSALDOneo[[#This Row],[Documento tipo]],Tabla7[#All],2,0) -> SERVICIOS | S11: =+VLOOKUP(COMPOSICIONSALDOneo[[#This Row],[CLIENTE]],Tabla5[],3,FALSE) -> Jujuy | T11: =IF(COMPOSICIONSALDOneo[[#This Row],[IMP. PRINCIPAL]]<0, "No vencido", IF(AND(COMPOSICIONSALDOneo[[#This Row],[FECHA VTO.]]-TODAY()>=1, COMPOSICIONSALDOneo[[#This Row],[FECHA VTO.]]-TODAY()<=5), "Vence 2-5 días", IF(COMPOSICIONSALDOneo[[#This Row],[FECHA VTO.]]-TODAY()<0, "Vencido", "No vencido"))) -> Vencido
A12: FCVTASERV | B12: 46139 | C12: Cliente 31 | D12: FC-1010 | F12: Dólares | G12: 489.85 | H12: 1 | I12: 489.85 | J12: 489.85 | K12: 46171 | L12: =IF(COMPOSICIONSALDOneo[[#This Row],[IMP. PRINCIPAL]] > 0, MAX(0, $A$1-COMPOSICIONSALDOneo[[#This Row],[FECHA VTO.]]), 0) -> 35 | M12: =UPPER(TEXT(COMPOSICIONSALDOneo[[#This Row],[FECHA VTO.]],"MMM")) -> MAY | N12: =TEXT(MONTH(COMPOSICIONSALDOneo[[#This Row],[FECHA VTO.]]),"00") -> 05 | O12: =+CONCATENATE(COMPOSICIONSALDOneo[[#This Row],[FECH]],"-",COMPOSICIONSALDOneo[[#This Row],[MES2]]) -> MAY-05 | P12: =IF(L12=0,"NO VENCIDO",IF(L12<30,"VENCIDO<30",IF(L12<60,"VENCIDO 30",IF(L12<90,"VENCIDO 60",IF(L12<150,"VENCIDO 90","VENCIDO>150"))))) -> VENCIDO 30 | Q12: =IF(COMPOSICIONSALDOneo[[#This Row],[DIAS DE MORA]]<1,"NO VENCIDO",IF(COMPOSICIONSALDOneo[[#This Row],[DIAS DE MORA]]>=1,"VENCIDO","INCOBRABLE")) -> VENCIDO | R12: =+VLOOKUP(COMPOSICIONSALDOneo[[#This Row],[Documento tipo]],Tabla7[#All],2,0) -> SERVICIOS | S12: =+VLOOKUP(COMPOSICIONSALDOneo[[#This Row],[CLIENTE]],Tabla5[],3,FALSE) -> Santiago del Estero | T12: =IF(COMPOSICIONSALDOneo[[#This Row],[IMP. PRINCIPAL]]<0, "No vencido", IF(AND(COMPOSICIONSALDOneo[[#This Row],[FECHA VTO.]]-TODAY()>=1, COMPOSICIONSALDOneo[[#This Row],[FECHA VTO.]]-TODAY()<=5), "Vence 2-5 días", IF(COMPOSICIONSALDOneo[[#This Row],[FECHA VTO.]]-TODAY()<0, "Vencido", "No vencido"))) -> Vencido
A13: COBRANZA | B13: 46166 | C13: Cliente 30 | D13: FC-1011 | E13: Mantenimiento | F13: Dólar Divisa | G13: 4707.75 | H13: 1 | I13: 4707.75 | J13: 4707.75 | K13: 46201 | L13: =IF(COMPOSICIONSALDOneo[[#This Row],[IMP. PRINCIPAL]] > 0, MAX(0, $A$1-COMPOSICIONSALDOneo[[#This Row],[FECHA VTO.]]), 0) -> 5 | M13: =UPPER(TEXT(COMPOSICIONSALDOneo[[#This Row],[FECHA VTO.]],"MMM")) -> JUN | N13: =TEXT(MONTH(COMPOSICIONSALDOneo[[#This Row],[FECHA VTO.]]),"00") -> 06 | O13: =+CONCATENATE(COMPOSICIONSALDOneo[[#This Row],[FECH]],"-",COMPOSICIONSALDOneo[[#This Row],[MES2]]) -> JUN-06 | P13: =IF(L13=0,"NO VENCIDO",IF(L13<30,"VENCIDO<30",IF(L13<60,"VENCIDO 30",IF(L13<90,"VENCIDO 60",IF(L13<150,"VENCIDO 90","VENCIDO>150"))))) -> VENCIDO<30 | Q13: =IF(COMPOSICIONSALDOneo[[#This Row],[DIAS DE MORA]]<1,"NO VENCIDO",IF(COMPOSICIONSALDOneo[[#This Row],[DIAS DE MORA]]>=1,"VENCIDO","INCOBRABLE")) -> VENCIDO | R13: =+VLOOKUP(COMPOSICIONSALDOneo[[#This Row],[Documento tipo]],Tabla7[#All],2,0) -> COBRANZAS | S13: =+VLOOKUP(COMPOSICIONSALDOneo[[#This Row],[CLIENTE]],Tabla5[],3,FALSE) -> Santiago del Estero | T13: =IF(COMPOSICIONSALDOneo[[#This Row],[IMP. PRINCIPAL]]<0, "No vencido", IF(AND(COMPOSICIONSALDOneo[[#This Row],[FECHA VTO.]]-TODAY()>=1, COMPOSICIONSALDOneo[[#This Row],[FECHA VTO.]]-TODAY()<=5), "Vence 2-5 días", IF(COMPOSICIONSALDOneo[[#This Row],[FECHA VTO.]]-TODAY()<0, "Vencido", "No vencido"))) -> Vencido
A14: NCSTOCK | B14: 46126 | C14: Cliente 13 | D14: FC-1012 | E14: Mantenimiento | F14: Dólar Divisa | G14: 249.34 | H14: 1 | I14: 249.34 | J14: 249.34 | K14: 46168 | L14: =IF(COMPOSICIONSALDOneo[[#This Row],[IMP. PRINCIPAL]] > 0, MAX(0, $A$1-COMPOSICIONSALDOneo[[#This Row],[FECHA VTO.]]), 0) -> 38 | M14: =UPPER(TEXT(COMPOSICIONSALDOneo[[#This Row],[FECHA VTO.]],"MMM")) -> MAY | N14: =TEXT(MONTH(COMPOSICIONSALDOneo[[#This Row],[FECHA VTO.]]),"00") -> 05 | O14: =+CONCATENATE(COMPOSICIONSALDOneo[[#This Row],[FECH]],"-",COMPOSICIONSALDOneo[[#This Row],[MES2]]) -> MAY-05 | P14: =IF(L14=0,"NO VENCIDO",IF(L14<30,"VENCIDO<30",IF(L14<60,"VENCIDO 30",IF(L14<90,"VENCIDO 60",IF(L14<150,"VENCIDO 90","VENCIDO>150"))))) -> VENCIDO 30 | Q14: =IF(COMPOSICIONSALDOneo[[#This Row],[DIAS DE MORA]]<1,"NO VENCIDO",IF(COMPOSICIONSALDOneo[[#This Row],[DIAS DE MORA]]>=1,"VENCIDO","INCOBRABLE")) -> VENCIDO | R14: =+VLOOKUP(COMPOSICIONSALDOneo[[#This Row],[Documento tipo]],Tabla7[#All],2,0) -> REPUESTOS | S14: =+VLOOKUP(COMPOSICIONSALDOneo[[#This Row],[CLIENTE]],Tabla5[],3,FALSE) -> Tucuman | T14: =IF(COMPOSICIONSALDOneo[[#This Row],[IMP. PRINCIPAL]]<0, "No vencido", IF(AND(COMPOSICIONSALDOneo[[#This Row],[FECHA VTO.]]-TODAY()>=1, COMPOSICIONSALDOneo[[#This Row],[FECHA VTO.]]-TODAY()<=5), "Vence 2-5 días", IF(COMPOSICIONSALDOneo[[#This Row],[FECHA VTO.]]-TODAY()<0, "Vencido", "No vencido"))) -> Vencido
A15: NCCEMIPYME-SER | B15: 46168 | C15: Cliente 52 | D15: FC-1013 | E15: Servicio de PM | F15: Dólar Divisa | G15: 9880.43 | H15: 1 | I15: 9880.43 | J15: 9880.43 | K15: 46199 | L15: =IF(COMPOSICIONSALDOneo[[#This Row],[IMP. PRINCIPAL]] > 0, MAX(0, $A$1-COMPOSICIONSALDOneo[[#This Row],[FECHA VTO.]]), 0) -> 7 | M15: =UPPER(TEXT(COMPOSICIONSALDOneo[[#This Row],[FECHA VTO.]],"MMM")) -> JUN | N15: =TEXT(MONTH(COMPOSICIONSALDOneo[[#This Row],[FECHA VTO.]]),"00") -> 06 | O15: =+CONCATENATE(COMPOSICIONSALDOneo[[#This Row],[FECH]],"-",COMPOSICIONSALDOneo[[#This Row],[MES2]]) -> JUN-06 | P15: =IF(L15=0,"NO VENCIDO",IF(L15<30,"VENCIDO<30",IF(L15<60,"VENCIDO 30",IF(L15<90,"VENCIDO 60",IF(L15<150,"VENCIDO 90","VENCIDO>150"))))) -> VENCIDO<30 | Q15: =IF(COMPOSICIONSALDOneo[[#This Row],[DIAS DE MORA]]<1,"NO VENCIDO",IF(COMPOSICIONSALDOneo[[#This Row],[DIAS DE MORA]]>=1,"VENCIDO","INCOBRABLE")) -> VENCIDO | R15: =+VLOOKUP(COMPOSICIONSALDOneo[[#This Row],[Documento tipo]],Tabla7[#All],2,0) -> SERVICIOS | S15: =+VLOOKUP(COMPOSICIONSALDOneo[[#This Row],[CLIENTE]],Tabla5[],3,FALSE) -> Catamarca | T15: =IF(COMPOSICIONSALDOneo[[#This Row],[IMP. PRINCIPAL]]<0, "No vencido", IF(AND(COMPOSICIONSALDOneo[[#This Row],[FECHA VTO.]]-TODAY()>=1, COMPOSICIONSALDOneo[[#This Row],[FECHA VTO.]]-TODAY()<=5), "Vence 2-5 días", IF(COMPOSICIONSALDOneo[[#This Row],[FECHA VTO.]]-TODAY()<0, "Vencido", "No vencido"))) -> Vencido
A16: NCCEMIPYME-SER | B16: 46175 | C16: Cliente 17 | D16: FC-1014 | E16: Mantenimiento | F16: Dólares | G16: 248.46 | H16: 1 | I16: 248.46 | J16: 248.46 | K16: 46201 | L16: =IF(COMPOSICIONSALDOneo[[#This Row],[IMP. PRINCIPAL]] > 0, MAX(0, $A$1-COMPOSICIONSALDOneo[[#This Row],[FECHA VTO.]]), 0) -> 5 | M16: =UPPER(TEXT(COMPOSICIONSALDOneo[[#This Row],[FECHA VTO.]],"MMM")) -> JUN | N16: =TEXT(MONTH(COMPOSICIONSALDOneo[[#This Row],[FECHA VTO.]]),"00") -> 06 | O16: =+CONCATENATE(COMPOSICIONSALDOneo[[#This Row],[FECH]],"-",COMPOSICIONSALDOneo[[#This Row],[MES2]]) -> JUN-06 | P16: =IF(L16=0,"NO VENCIDO",IF(L16<30,"VENCIDO<30",IF(L16<60,"VENCIDO 30",IF(L16<90,"VENCIDO 60",IF(L16<150,"VENCIDO 90","VENCIDO>150"))))) -> VENCIDO<30 | Q16: =IF(COMPOSICIONSALDOneo[[#This Row],[DIAS DE MORA]]<1,"NO VENCIDO",IF(COMPOSICIONSALDOneo[[#This Row],[DIAS DE MORA]]>=1,"VENCIDO","INCOBRABLE")) -> VENCIDO | R16: =+VLOOKUP(COMPOSICIONSALDOneo[[#This Row],[Documento tipo]],Tabla7[#All],2,0) -> SERVICIOS | S16: =+VLOOKUP(COMPOSICIONSALDOneo[[#This Row],[CLIENTE]],Tabla5[],3,FALSE) -> Jujuy | T16: =IF(COMPOSICIONSALDOneo[[#This Row],[IMP. PRINCIPAL]]<0, "No vencido", IF(AND(COMPOSICIONSALDOneo[[#This Row],[FECHA VTO.]]-TODAY()>=1, COMPOSICIONSALDOneo[[#This Row],[FECHA VTO.]]-TODAY()<=5), "Vence 2-5 días", IF(COMPOSICIONSALDOneo[[#This Row],[FECHA VTO.]]-TODAY()<0, "Vencido", "No vencido"))) -> Vencido
A17: NDCDVM | B17: 46045 | C17: Cliente 42 | D17: FC-1015 | F17: Pesos | G17: 158.99 | H17: 1060.73 | I17: 158.99 | J17: 158.99 | K17: 46084 | L17: =IF(COMPOSICIONSALDOneo[[#This Row],[IMP. PRINCIPAL]] > 0, MAX(0, $A$1-COMPOSICIONSALDOneo[[#This Row],[FECHA VTO.]]), 0) -> 122 | M17: =UPPER(TEXT(COMPOSICIONSALDOneo[[#This Row],[FECHA VTO.]],"MMM")) -> MAR | N17: =TEXT(MONTH(COMPOSICIONSALDOneo[[#This Row],[FECHA VTO.]]),"00") -> 03 | O17: =+CONCATENATE(COMPOSICIONSALDOneo[[#This Row],[FECH]],"-",COMPOSICIONSALDOneo[[#This Row],[MES2]]) -> MAR-03 | P17: =IF(L17=0,"NO VENCIDO",IF(L17<30,"VENCIDO<30",IF(L17<60,"VENCIDO 30",IF(L17<90,"VENCIDO 60",IF(L17<150,"VENCIDO 90","VENCIDO>150"))))) -> VENCIDO 90 | Q17: =IF(COMPOSICIONSALDOneo[[#This Row],[DIAS DE MORA]]<1,"NO VENCIDO",IF(COMPOSICIONSALDOneo[[#This Row],[DIAS DE MORA]]>=1,"VENCIDO","INCOBRABLE")) -> VENCIDO | R17: =+VLOOKUP(COMPOSICIONSALDOneo[[#This Row],[Documento tipo]],Tabla7[#All],2,0) -> MAQUINAS | S17: =+VLOOKUP(COMPOSICIONSALDOneo[[#This Row],[CLIENTE]],Tabla5[],3,FALSE) -> Salta | T17: =IF(COMPOSICIONSALDOneo[[#This Row],[IMP. PRINCIPAL]]<0, "No vencido", IF(AND(COMPOSICIONSALDOneo[[#This Row],[FECHA VTO.]]-TODAY()>=1, COMPOSICIONSALDOneo[[#This Row],[FECHA VTO.]]-TODAY()<=5), "Vence 2-5 días", IF(COMPOSICIONSALDOneo[[#This Row],[FECHA VTO.]]-TODAY()<0, "Vencido", "No vencido"))) -> Vencido
A18: NCVDCR | B18: 46157 | C18: Cliente 18 | D18: FC-1016 | E18: Venta maquina | F18: Dólar Divisa | G18: 1489.85 | H18: 1 | I18: 1489.85 | J18: 1489.85 | K18: 46173 | L18: =IF(COMPOSICIONSALDOneo[[#This Row],[IMP. PRINCIPAL]] > 0, MAX(0, $A$1-COMPOSICIONSALDOneo[[#This Row],[FECHA VTO.]]), 0) -> 33 | M18: =UPPER(TEXT(COMPOSICIONSALDOneo[[#This Row],[FECHA VTO.]],"MMM")) -> MAY | N18: =TEXT(MONTH(COMPOSICIONSALDOneo[[#This Row],[FECHA VTO.]]),"00") -> 05 | O18: =+CONCATENATE(COMPOSICIONSALDOneo[[#This Row],[FECH]],"-",COMPOSICIONSALDOneo[[#This Row],[MES2]]) -> MAY-05 | P18: =IF(L18=0,"NO VENCIDO",IF(L18<30,"VENCIDO<30",IF(L18<60,"VENCIDO 30",IF(L18<90,"VENCIDO 60",IF(L18<150,"VENCIDO 90","VENCIDO>150"))))) -> VENCIDO 30 | Q18: =IF(COMPOSICIONSALDOneo[[#This Row],[DIAS DE MORA]]<1,"NO VENCIDO",IF(COMPOSICIONSALDOneo[[#This Row],[DIAS DE MORA]]>=1,"VENCIDO","INCOBRABLE")) -> VENCIDO | R18: =+VLOOKUP(COMPOSICIONSALDOneo[[#This Row],[Documento tipo]],Tabla7[#All],2,0) -> REPUESTOS | S18: =+VLOOKUP(COMPOSICIONSALDOneo[[#This Row],[CLIENTE]],Tabla5[],3,FALSE) -> Catamarca | T18: =IF(COMPOSICIONSALDOneo[[#This Row],[IMP. PRINCIPAL]]<0, "No vencido", IF(AND(COMPOSICIONSALDOneo[[#This Row],[FECHA VTO.]]-TODAY()>=1, COMPOSICIONSALDOneo[[#This Row],[FECHA VTO.]]-TODAY()<=5), "Vence 2-5 días", IF(COMPOSICIONSALDOneo[[#This Row],[FECHA VTO.]]-TODAY()<0, "Vencido", "No vencido"))) -> Vencido
A19: COBRANZA | B19: 46100 | C19: Cliente 18 | D19: FC-1017 | E19: Facturacion mensual | F19: Dólar Divisa | G19: 378.82 | H19: 1 | I19: 378.82 | J19: 378.82 | K19: 46134 | L19: =IF(COMPOSICIONSALDOneo[[#This Row],[IMP. PRINCIPAL]] > 0, MAX(0, $A$1-COMPOSICIONSALDOneo[[#This Row],[FECHA VTO.]]), 0) -> 72 | M19: =UPPER(TEXT(COMPOSICIONSALDOneo[[#This Row],[FECHA VTO.]],"MMM")) -> ABR | N19: =TEXT(MONTH(COMPOSICIONSALDOneo[[#This Row],[FECHA VTO.]]),"00") -> 04 | O19: =+CONCATENATE(COMPOSICIONSALDOneo[[#This Row],[FECH]],"-",COMPOSICIONSALDOneo[[#This Row],[MES2]]) -> ABR-04 | P19: =IF(L19=0,"NO VENCIDO",IF(L19<30,"VENCIDO<30",IF(L19<60,"VENCIDO 30",IF(L19<90,"VENCIDO 60",IF(L19<150,"VENCIDO 90","VENCIDO>150"))))) -> VENCIDO 60 | Q19: =IF(COMPOSICIONSALDOneo[[#This Row],[DIAS DE MORA]]<1,"NO VENCIDO",IF(COMPOSICIONSALDOneo[[#This Row],[DIAS DE MORA]]>=1,"VENCIDO","INCOBRABLE")) -> VENCIDO | R19: =+VLOOKUP(COMPOSICIONSALDOneo[[#This Row],[Documento tipo]],Tabla7[#All],2,0) -> COBRANZAS | S19: =+VLOOKUP(COMPOSICIONSALDOneo[[#This Row],[CLIENTE]],Tabla5[],3,FALSE) -> Catamarca | T19: =IF(COMPOSICIONSALDOneo[[#This Row],[IMP. PRINCIPAL]]<0, "No vencido", IF(AND(COMPOSICIONSALDOneo[[#This Row],[FECHA VTO.]]-TODAY()>=1, COMPOSICIONSALDOneo[[#This Row],[FECHA VTO.]]-TODAY()<=5), "Vence 2-5 días", IF(COMPOSICIONSALDOneo[[#This Row],[FECHA VTO.]]-TODAY()<0, "Vencido", "No vencido"))) -> Vencido
A20: NCCEMIPYME-SER | B20: 46159 | C20: Cliente 59 | D20: FC-1018 | E20: Servicio de PM | F20: Dólar Divisa | G20: 5103.09 | H20: 1 | I20: 5103.09 | J20: 5103.09 | K20: 46191 | L20: =IF(COMPOSICIONSALDOneo[[#This Row],[IMP. PRINCIPAL]] > 0, MAX(0, $A$1-COMPOSICIONSALDOneo[[#This Row],[FECHA VTO.]]), 0) -> 15 | M20: =UPPER(TEXT(COMPOSICIONSALDOneo[[#This Row],[FECHA VTO.]],"MMM")) -> JUN | N20: =TEXT(MONTH(COMPOSICIONSALDOneo[[#This Row],[FECHA VTO.]]),"00") -> 06 | O20: =+CONCATENATE(COMPOSICIONSALDOneo[[#This Row],[FECH]],"-",COMPOSICIONSALDOneo[[#This Row],[MES2]]) -> JUN-06 | P20: =IF(L20=0,"NO VENCIDO",IF(L20<30,"VENCIDO<30",IF(L20<60,"VENCIDO 30",IF(L20<90,"VENCIDO 60",IF(L20<150,"VENCIDO 90","VENCIDO>150"))))) -> VENCIDO<30 | Q20: =IF(COMPOSICIONSALDOneo[[#This Row],[DIAS DE MORA]]<1,"NO VENCIDO",IF(COMPOSICIONSALDOneo[[#This Row],[DIAS DE MORA]]>=1,"VENCIDO","INCOBRABLE")) -> VENCIDO | R20: =+VLOOKUP(COMPOSICIONSALDOneo[[#This Row],[Documento tipo]],Tabla7[#All],2,0) -> SERVICIOS | S20: =+VLOOKUP(COMPOSICIONSALDOneo[[#This Row],[CLIENTE]],Tabla5[],3,FALSE) -> Tucuman | T20: =IF(COMPOSICIONSALDOneo[[#This Row],[IMP. PRINCIPAL]]<0, "No vencido", IF(AND(COMPOSICIONSALDOneo[[#This Row],[FECHA VTO.]]-TODAY()>=1, COMPOSICIONSALDOneo[[#This Row],[FECHA VTO.]]-TODAY()<=5), "Vence 2-5 días", IF(COMPOSICIONSALDOneo[[#This Row],[FECHA VTO.]]-TODAY()<0, "Vencido", "No vencido"))) -> Vencido
A21: FVMZFLP | B21: 46260 | C21: Cliente 27 | D21: FC-1019 | E21: Venta repuestos | F21: Dólar Divisa | G21: 16187.59 | H21: 1 | I21: 16187.59 | J21: 16187.59 | K21: 46280 | L21: =IF(COMPOSICIONSALDOneo[[#This Row],[IMP. PRINCIPAL]] > 0, MAX(0, $A$1-COMPOSICIONSALDOneo[[#This Row],[FECHA VTO.]]), 0) -> 0 | M21: =UPPER(TEXT(COMPOSICIONSALDOneo[[#This Row],[FECHA VTO.]],"MMM")) -> SEPT | N21: =TEXT(MONTH(COMPOSICIONSALDOneo[[#This Row],[FECHA VTO.]]),"00") -> 09 | O21: =+CONCATENATE(COMPOSICIONSALDOneo[[#This Row],[FECH]],"-",COMPOSICIONSALDOneo[[#This Row],[MES2]]) -> SEPT-09 | P21: =IF(L21=0,"NO VENCIDO",IF(L21<30,"VENCIDO<30",IF(L21<60,"VENCIDO 30",IF(L21<90,"VENCIDO 60",IF(L21<150,"VENCIDO 90","VENCIDO>150"))))) -> NO VENCIDO | Q21: =IF(COMPOSICIONSALDOneo[[#This Row],[DIAS DE MORA]]<1,"NO VENCIDO",IF(COMPOSICIONSALDOneo[[#This Row],[DIAS DE MORA]]>=1,"VENCIDO","INCOBRABLE")) -> NO VENCIDO | R21: =+VLOOKUP(COMPOSICIONSALDOneo[[#This Row],[Documento tipo]],Tabla7[#All],2,0) -> MAQUINAS | S21: =+VLOOKUP(COMPOSICIONSALDOneo[[#This Row],[CLIENTE]],Tabla5[],3,FALSE) -> Salta | T21: =IF(COMPOSICIONSALDOneo[[#This Row],[IMP. PRINCIPAL]]<0, "No vencido", IF(AND(COMPOSICIONSALDOneo[[#This Row],[FECHA VTO.]]-TODAY()>=1, COMPOSICIONSALDOneo[[#This Row],[FECHA VTO.]]-TODAY()<=5), "Vence 2-5 días", IF(COMPOSICIONSALDOneo[[#This Row],[FECHA VTO.]]-TODAY()<0, "Vencido", "No vencido"))) -> No vencido
A22: FCEMIPYME-MAQ | B22: 46093 | C22: Cliente 58 | D22: FC-1020 | E22: Service programado | F22: Pesos | G22: 164.54 | H22: 1086.65 | I22: 164.54 | J22: 164.54 | K22: 46108 | L22: =IF(COMPOSICIONSALDOneo[[#This Row],[IMP. PRINCIPAL]] > 0, MAX(0, $A$1-COMPOSICIONSALDOneo[[#This Row],[FECHA VTO.]]), 0) -> 98 | M22: =UPPER(TEXT(COMPOSICIONSALDOneo[[#This Row],[FECHA VTO.]],"MMM")) -> MAR | N22: =TEXT(MONTH(COMPOSICIONSALDOneo[[#This Row],[FECHA VTO.]]),"00") -> 03 | O22: =+CONCATENATE(COMPOSICIONSALDOneo[[#This Row],[FECH]],"-",COMPOSICIONSALDOneo[[#This Row],[MES2]]) -> MAR-03 | P22: =IF(L22=0,"NO VENCIDO",IF(L22<30,"VENCIDO<30",IF(L22<60,"VENCIDO 30",IF(L22<90,"VENCIDO 60",IF(L22<150,"VENCIDO 90","VENCIDO>150"))))) -> VENCIDO 90 | Q22: =IF(COMPOSICIONSALDOneo[[#This Row],[DIAS DE MORA]]<1,"NO VENCIDO",IF(COMPOSICIONSALDOneo[[#This Row],[DIAS DE MORA]]>=1,"VENCIDO","INCOBRABLE")) -> VENCIDO | R22: =+VLOOKUP(COMPOSICIONSALDOneo[[#This Row],[Documento tipo]],Tabla7[#All],2,0) -> MAQUINAS | S22: =+VLOOKUP(COMPOSICIONSALDOneo[[#This Row],[CLIENTE]],Tabla5[],3,FALSE) -> Catamarca | T22: =IF(COMPOSICIONSALDOneo[[#This Row],[IMP. PRINCIPAL]]<0, "No vencido", IF(AND(COMPOSICIONSALDOneo[[#This Row],[FECHA VTO.]]-TODAY()>=1, COMPOSICIONSALDOneo[[#This Row],[FECHA VTO.]]-TODAY()<=5), "Vence 2-5 días", IF(COMPOSICIONSALDOneo[[#This Row],[FECHA VTO.]]-TODAY()<0, "Vencido", "No vencido"))) -> Vencido
A23: REC10.5 | B23: 46264 | C23: Cliente 34 | D23: FC-1021 | E23: Venta repuestos | F23: Pesos | G23: 9788.11 | H23: 1038.06 | I23: 9788.11 | J23: 9788.11 | K23: 46280 | L23: =IF(COMPOSICIONSALDOneo[[#This Row],[IMP. PRINCIPAL]] > 0, MAX(0, $A$1-COMPOSICIONSALDOneo[[#This Row],[FECHA VTO.]]), 0) -> 0 | M23: =UPPER(TEXT(COMPOSICIONSALDOneo[[#This Row],[FECHA VTO.]],"MMM")) -> SEPT | N23: =TEXT(MONTH(COMPOSICIONSALDOneo[[#This Row],[FECHA VTO.]]),"00") -> 09 | O23: =+CONCATENATE(COMPOSICIONSALDOneo[[#This Row],[FECH]],"-",COMPOSICIONSALDOneo[[#This Row],[MES2]]) -> SEPT-09 | P23: =IF(L23=0,"NO VENCIDO",IF(L23<30,"VENCIDO<30",IF(L23<60,"VENCIDO 30",IF(L23<90,"VENCIDO 60",IF(L23<150,"VENCIDO 90","VENCIDO>150"))))) -> NO VENCIDO | Q23: =IF(COMPOSICIONSALDOneo[[#This Row],[DIAS DE MORA]]<1,"NO VENCIDO",IF(COMPOSICIONSALDOneo[[#This Row],[DIAS DE MORA]]>=1,"VENCIDO","INCOBRABLE")) -> NO VENCIDO | R23: =+VLOOKUP(COMPOSICIONSALDOneo[[#This Row],[Documento tipo]],Tabla7[#All],2,0) -> MAQUINAS | S23: =+VLOOKUP(COMPOSICIONSALDOneo[[#This Row],[CLIENTE]],Tabla5[],3,FALSE) -> Jujuy | T23: =IF(COMPOSICIONSALDOneo[[#This Row],[IMP. PRINCIPAL]]<0, "No vencido", IF(AND(COMPOSICIONSALDOneo[[#This Row],[FECHA VTO.]]-TODAY()>=1, COMPOSICIONSALDOneo[[#This Row],[FECHA VTO.]]-TODAY()<=5), "Vence 2-5 días", IF(COMPOSICIONSALDOneo[[#This Row],[FECHA VTO.]]-TODAY()<0, "Vencido", "No vencido"))) -> No vencido
A24: NCCEMIPYME-SER | B24: 46124 | C24: Cliente 51 | D24: FC-1022 | E24: Facturacion mensual | F24: Dólar Divisa | G24: 245.79 | H24: 1 | I24: 245.79 | J24: 245.79 | K24: 46142 | L24: =IF(COMPOSICIONSALDOneo[[#This Row],[IMP. PRINCIPAL]] > 0, MAX(0, $A$1-COMPOSICIONSALDOneo[[#This Row],[FECHA VTO.]]), 0) -> 64 | M24: =UPPER(TEXT(COMPOSICIONSALDOneo[[#This Row],[FECHA VTO.]],"MMM")) -> ABR | N24: =TEXT(MONTH(COMPOSICIONSALDOneo[[#This Row],[FECHA VTO.]]),"00") -> 04 | O24: =+CONCATENATE(COMPOSICIONSALDOneo[[#This Row],[FECH]],"-",COMPOSICIONSALDOneo[[#This Row],[MES2]]) -> ABR-04 | P24: =IF(L24=0,"NO VENCIDO",IF(L24<30,"VENCIDO<30",IF(L24<60,"VENCIDO 30",IF(L24<90,"VENCIDO 60",IF(L24<150,"VENCIDO 90","VENCIDO>150"))))) -> VENCIDO 60 | Q24: =IF(COMPOSICIONSALDOneo[[#This Row],[DIAS DE MORA]]<1,"NO VENCIDO",IF(COMPOSICIONSALDOneo[[#This Row],[DIAS DE MORA]]>=1,"VENCIDO","INCOBRABLE")) -> VENCIDO | R24: =+VLOOKUP(COMPOSICIONSALDOneo[[#This Row],[Documento tipo]],Tabla7[#All],2,0) -> SERVICIOS | S24: =+VLOOKUP(COMPOSICIONSALDOneo[[#This Row],[CLIENTE]],Tabla5[],3,FALSE) -> Tucuman | T24: =IF(COMPOSICIONSALDOneo[[#This Row],[IMP. PRINCIPAL]]<0, "No vencido", IF(AND(COMPOSICIONSALDOneo[[#This Row],[FECHA VTO.]]-TODAY()>=1, COMPOSICIONSALDOneo[[#This Row],[FECHA VTO.]]-TODAY()<=5), "Vence 2-5 días", IF(COMPOSICIONSALDOneo[[#This Row],[FECHA VTO.]]-TODAY()<0, "Vencido", "No vencido"))) -> Vencido
A25: FCEMIPYME-SER | B25: 46143 | C25: Cliente 60 | D25: FC-1023 | E25: Servicio de PM | F25: Pesos | G25: 975.71 | H25: 1064.63 | I25: 975.71 | J25: 975.71 | K25: 46159 | L25: =IF(COMPOSICIONSALDOneo[[#This Row],[IMP. PRINCIPAL]] > 0, MAX(0, $A$1-COMPOSICIONSALDOneo[[#This Row],[FECHA VTO.]]), 0) -> 47 | M25: =UPPER(TEXT(COMPOSICIONSALDOneo[[#This Row],[FECHA VTO.]],"MMM")) -> MAY | N25: =TEXT(MONTH(COMPOSICIONSALDOneo[[#This Row],[FECHA VTO.]]),"00") -> 05 | O25: =+CONCATENATE(COMPOSICIONSALDOneo[[#This Row],[FECH]],"-",COMPOSICIONSALDOneo[[#This Row],[MES2]]) -> MAY-05 | P25: =IF(L25=0,"NO VENCIDO",IF(L25<30,"VENCIDO<30",IF(L25<60,"VENCIDO 30",IF(L25<90,"VENCIDO 60",IF(L25<150,"VENCIDO 90","VENCIDO>150"))))) -> VENCIDO 30 | Q25: =IF(COMPOSICIONSALDOneo[[#This Row],[DIAS DE MORA]]<1,"NO VENCIDO",IF(COMPOSICIONSALDOneo[[#This Row],[DIAS DE MORA]]>=1,"VENCIDO","INCOBRABLE")) -> VENCIDO | R25: =+VLOOKUP(COMPOSICIONSALDOneo[[#This Row],[Documento tipo]],Tabla7[#All],2,0) -> SERVICIOS | S25: =+VLOOKUP(COMPOSICIONSALDOneo[[#This Row],[CLIENTE]],Tabla5[],3,FALSE) -> Tucuman | T25: =IF(COMPOSICIONSALDOneo[[#This Row],[IMP. PRINCIPAL]]<0, "No vencido", IF(AND(COMPOSICIONSALDOneo[[#This Row],[FECHA VTO.]]-TODAY()>=1, COMPOSICIONSALDOneo[[#This Row],[FECHA VTO.]]-TODAY()<=5), "Vence 2-5 días", IF(COMPOSICIONSALDOneo[[#This Row],[FECHA VTO.]]-TODAY()<0, "Vencido", "No vencido"))) -> Vencido
A26: COBRANZA | B26: 46231 | C26: Cliente 11 | D26: FC-1024 | E26: Servicio de PM | F26: Pesos | G26: 16930.22 | H26: 1053.91 | I26: 16930.22 | J26: 16930.22 | K26: 46251 | L26: =IF(COMPOSICIONSALDOneo[[#This Row],[IMP. PRINCIPAL]] > 0, MAX(0, $A$1-COMPOSICIONSALDOneo[[#This Row],[FECHA VTO.]]), 0) -> 0 | M26: =UPPER(TEXT(COMPOSICIONSALDOneo[[#This Row],[FECHA VTO.]],"MMM")) -> AGO | N26: =TEXT(MONTH(COMPOSICIONSALDOneo[[#This Row],[FECHA VTO.]]),"00") -> 08 | O26: =+CONCATENATE(COMPOSICIONSALDOneo[[#This Row],[FECH]],"-",COMPOSICIONSALDOneo[[#This Row],[MES2]]) -> AGO-08 | P26: =IF(L26=0,"NO VENCIDO",IF(L26<30,"VENCIDO<30",IF(L26<60,"VENCIDO 30",IF(L26<90,"VENCIDO 60",IF(L26<150,"VENCIDO 90","VENCIDO>150"))))) -> NO VENCIDO | Q26: =IF(COMPOSICIONSALDOneo[[#This Row],[DIAS DE MORA]]<1,"NO VENCIDO",IF(COMPOSICIONSALDOneo[[#This Row],[DIAS DE MORA]]>=1,"VENCIDO","INCOBRABLE")) -> NO VENCIDO | R26: =+VLOOKUP(COMPOSICIONSALDOneo[[#This Row],[Documento tipo]],Tabla7[#All],2,0) -> COBRANZAS | S26: =+VLOOKUP(COMPOSICIONSALDOneo[[#This Row],[CLIENTE]],Tabla5[],3,FALSE) -> Catamarca | T26: =IF(COMPOSICIONSALDOneo[[#This Row],[IMP. PRINCIPAL]]<0, "No vencido", IF(AND(COMPOSICIONSALDOneo[[#This Row],[FECHA VTO.]]-TODAY()>=1, COMPOSICIONSALDOneo[[#This Row],[FECHA VTO.]]-TODAY()<=5), "Vence 2-5 días", IF(COMPOSICIONSALDOneo[[#This Row],[FECHA VTO.]]-TODAY()<0, "Vencido", "No vencido"))) -> No vencido
A27: RCM | B27: 46158 | C27: Cliente 20 | D27: FC-1025 | E27: Facturacion mensual | F27: Dólar Divisa | G27: 7733.95 | H27: 1 | I27: 7733.95 | J27: 7733.95 | K27: 46185 | L27: =IF(COMPOSICIONSALDOneo[[#This Row],[IMP. PRINCIPAL]] > 0, MAX(0, $A$1-COMPOSICIONSALDOneo[[#This Row],[FECHA VTO.]]), 0) -> 21 | M27: =UPPER(TEXT(COMPOSICIONSALDOneo[[#This Row],[FECHA VTO.]],"MMM")) -> JUN | N27: =TEXT(MONTH(COMPOSICIONSALDOneo[[#This Row],[FECHA VTO.]]),"00") -> 06 | O27: =+CONCATENATE(COMPOSICIONSALDOneo[[#This Row],[FECH]],"-",COMPOSICIONSALDOneo[[#This Row],[MES2]]) -> JUN-06 | P27: =IF(L27=0,"NO VENCIDO",IF(L27<30,"VENCIDO<30",IF(L27<60,"VENCIDO 30",IF(L27<90,"VENCIDO 60",IF(L27<150,"VENCIDO 90","VENCIDO>150"))))) -> VENCIDO<30 | Q27: =IF(COMPOSICIONSALDOneo[[#This Row],[DIAS DE MORA]]<1,"NO VENCIDO",IF(COMPOSICIONSALDOneo[[#This Row],[DIAS DE MORA]]>=1,"VENCIDO","INCOBRABLE")) -> VENCIDO | R27: =+VLOOKUP(COMPOSICIONSALDOneo[[#This Row],[Documento tipo]],Tabla7[#All],2,0) -> MAQUINAS | S27: =+VLOOKUP(COMPOSICIONSALDOneo[[#This Row],[CLIENTE]],Tabla5[],3,FALSE) -> Jujuy | T27: =IF(COMPOSICIONSALDOneo[[#This Row],[IMP. PRINCIPAL]]<0, "No vencido", IF(AND(COMPOSICIONSALDOneo[[#This Row],[FECHA VTO.]]-TODAY()>=1, COMPOSICIONSALDOneo[[#This Row],[FECHA VTO.]]-TODAY()<=5), "Vence 2-5 días", IF(COMPOSICIONSALDOneo[[#This Row],[FECHA VTO.]]-TODAY()<0, "Vencido", "No vencido"))) -> Vencido
A28: COBRANZA | B28: 46212 | C28: Cliente 54 | D28: FC-1026 | E28: OT reparacion | F28: Pesos | G28: 10951.14 | H28: 1010.74 | I28: 10951.14 | J28: 10951.14 | K28: 46237 | L28: =IF(COMPOSICIONSALDOneo[[#This Row],[IMP. PRINCIPAL]] > 0, MAX(0, $A$1-COMPOSICIONSALDOneo[[#This Row],[FECHA VTO.]]), 0) -> 0 | M28: =UPPER(TEXT(COMPOSICIONSALDOneo[[#This Row],[FECHA VTO.]],"MMM")) -> AGO | N28: =TEXT(MONTH(COMPOSICIONSALDOneo[[#This Row],[FECHA VTO.]]),"00") -> 08 | O28: =+CONCATENATE(COMPOSICIONSALDOneo[[#This Row],[FECH]],"-",COMPOSICIONSALDOneo[[#This Row],[MES2]]) -> AGO-08 | P28: =IF(L28=0,"NO VENCIDO",IF(L28<30,"VENCIDO<30",IF(L28<60,"VENCIDO 30",IF(L28<90,"VENCIDO 60",IF(L28<150,"VENCIDO 90","VENCIDO>150"))))) -> NO VENCIDO | Q28: =IF(COMPOSICIONSALDOneo[[#This Row],[DIAS DE MORA]]<1,"NO VENCIDO",IF(COMPOSICIONSALDOneo[[#This Row],[DIAS DE MORA]]>=1,"VENCIDO","INCOBRABLE")) -> NO VENCIDO | R28: =+VLOOKUP(COMPOSICIONSALDOneo[[#This Row],[Documento tipo]],Tabla7[#All],2,0) -> COBRANZAS | S28: =+VLOOKUP(COMPOSICIONSALDOneo[[#This Row],[CLIENTE]],Tabla5[],3,FALSE) -> Tucuman | T28: =IF(COMPOSICIONSALDOneo[[#This Row],[IMP. PRINCIPAL]]<0, "No vencido", IF(AND(COMPOSICIONSALDOneo[[#This Row],[FECHA VTO.]]-TODAY()>=1, COMPOSICIONSALDOneo[[#This Row],[FECHA VTO.]]-TODAY()<=5), "Vence 2-5 días", IF(COMPOSICIONSALDOneo[[#This Row],[FECHA VTO.]]-TODAY()<0, "Vencido", "No vencido"))) -> No vencido
A29: FCEMIPYME-MAQ | B29: 46140 | C29: Cliente 11 | D29: FC-1027 | E29: Venta repuestos | F29: Dólar Divisa | G29: 438.15 | H29: 1 | I29: 438.15 | J29: 438.15 | K29: 46168 | L29: =IF(COMPOSICIONSALDOneo[[#This Row],[IMP. PRINCIPAL]] > 0, MAX(0, $A$1-COMPOSICIONSALDOneo[[#This Row],[FECHA VTO.]]), 0) -> 38 | M29: =UPPER(TEXT(COMPOSICIONSALDOneo[[#This Row],[FECHA VTO.]],"MMM")) -> MAY | N29: =TEXT(MONTH(COMPOSICIONSALDOneo[[#This Row],[FECHA VTO.]]),"00") -> 05 | O29: =+CONCATENATE(COMPOSICIONSALDOneo[[#This Row],[FECH]],"-",COMPOSICIONSALDOneo[[#This Row],[MES2]]) -> MAY-05 | P29: =IF(L29=0,"NO VENCIDO",IF(L29<30,"VENCIDO<30",IF(L29<60,"VENCIDO 30",IF(L29<90,"VENCIDO 60",IF(L29<150,"VENCIDO 90","VENCIDO>150"))))) -> VENCIDO 30 | Q29: =IF(COMPOSICIONSALDOneo[[#This Row],[DIAS DE MORA]]<1,"NO VENCIDO",IF(COMPOSICIONSALDOneo[[#This Row],[DIAS DE MORA]]>=1,"VENCIDO","INCOBRABLE")) -> VENCIDO | R29: =+VLOOKUP(COMPOSICIONSALDOneo[[#This Row],[Documento tipo]],Tabla7[#All],2,0) -> MAQUINAS | S29: =+VLOOKUP(COMPOSICIONSALDOneo[[#This Row],[CLIENTE]],Tabla5[],3,FALSE) -> Catamarca | T29: =IF(COMPOSICIONSALDOneo[[#This Row],[IMP. PRINCIPAL]]<0, "No vencido", IF(AND(COMPOSICIONSALDOneo[[#This Row],[FECHA VTO.]]-TODAY()>=1, COMPOSICIONSALDOneo[[#This Row],[FECHA VTO.]]-TODAY()<=5), "Vence 2-5 días", IF(COMPOSICIONSALDOneo[[#This Row],[FECHA VTO.]]-TODAY()<0, "Vencido", "No vencido"))) -> Vencido
... A33: FCEMIPYME-MAQ | B33: 46247 | C33: Cliente 52 | D33: FC-1031 | E33: Mantenimiento | F33: Dólares | G33: 14984.12 | H33: 1 | I33: 14984.12 | J33: 14984.12 | K33: 46264 | L33: =IF(COMPOSICIONSALDOneo[[#This Row],[IMP. PRINCIPAL]] > 0, MAX(0, $A$1-COMPOSICIONSALDOneo[[#This Row],[FECHA VTO.]]), 0) -> 0 | M33: =UPPER(TEXT(COMPOSICIONSALDOneo[[#This Row],[FECHA VTO.]],"MMM")) -> AGO | N33: =TEXT(MONTH(COMPOSICIONSALDOneo[[#This Row],[FECHA VTO.]]),"00") -> 08 | O33: =+CONCATENATE(COMPOSICIONSALDOneo[[#This Row],[FECH]],"-",COMPOSICIONSALDOneo[[#This Row],[MES2]]) -> AGO-08 | P33: =IF(L33=0,"NO VENCIDO",IF(L33<30,"VENCIDO<30",IF(L33<60,"VENCIDO 30",IF(L33<90,"VENCIDO 60",IF(L33<150,"VENCIDO 90","VENCIDO>150"))))) -> NO VENCIDO | Q33: =IF(COMPOSICIONSALDOneo[[#This Row],[DIAS DE MORA]]<1,"NO VENCIDO",IF(COMPOSICIONSALDOneo[[#This Row],[DIAS DE MORA]]>=1,"VENCIDO","INCOBRABLE")) -> NO VENCIDO | R33: =+VLOOKUP(COMPOSICIONSALDOneo[[#This Row],[Documento tipo]],Tabla7[#All],2,0) -> MAQUINAS | S33: =+VLOOKUP(COMPOSICIONSALDOneo[[#This Row],[CLIENTE]],Tabla5[],3,FALSE) -> Catamarca | T33: =IF(COMPOSICIONSALDOneo[[#This Row],[IMP. PRINCIPAL]]<0, "No vencido", IF(AND(COMPOSICIONSALDOneo[[#This Row],[FECHA VTO.]]-TODAY()>=1, COMPOSICIONSALDOneo[[#This Row],[FECHA VTO.]]-TODAY()<=5), "Vence 2-5 días", IF(COMPOSICIONSALDOneo[[#This Row],[FECHA VTO.]]-TODAY()<0, "Vencido", "No vencido"))) -> No vencido
A34: RC | B34: 46160 | C34: Cliente 7 | D34: FC-1032 | F34: Dólar Divisa | G34: 6258.53 | H34: 1 | I34: 6258.53 | J34: 6258.53 | K34: 46191 | L34: =IF(COMPOSICIONSALDOneo[[#This Row],[IMP. PRINCIPAL]] > 0, MAX(0, $A$1-COMPOSICIONSALDOneo[[#This Row],[FECHA VTO.]]), 0) -> 15 | M34: =UPPER(TEXT(COMPOSICIONSALDOneo[[#This Row],[FECHA VTO.]],"MMM")) -> JUN | N34: =TEXT(MONTH(COMPOSICIONSALDOneo[[#This Row],[FECHA VTO.]]),"00") -> 06 | O34: =+CONCATENATE(COMPOSICIONSALDOneo[[#This Row],[FECH]],"-",COMPOSICIONSALDOneo[[#This Row],[MES2]]) -> JUN-06 | P34: =IF(L34=0,"NO VENCIDO",IF(L34<30,"VENCIDO<30",IF(L34<60,"VENCIDO 30",IF(L34<90,"VENCIDO 60",IF(L34<150,"VENCIDO 90","VENCIDO>150"))))) -> VENCIDO<30 | Q34: =IF(COMPOSICIONSALDOneo[[#This Row],[DIAS DE MORA]]<1,"NO VENCIDO",IF(COMPOSICIONSALDOneo[[#This Row],[DIAS DE MORA]]>=1,"VENCIDO","INCOBRABLE")) -> VENCIDO | R34: =+VLOOKUP(COMPOSICIONSALDOneo[[#This Row],[Documento tipo]],Tabla7[#All],2,0) -> REPUESTOS | S34: =+VLOOKUP(COMPOSICIONSALDOneo[[#This Row],[CLIENTE]],Tabla5[],3,FALSE) -> Catamarca | T34: =IF(COMPOSICIONSALDOneo[[#This Row],[IMP. PRINCIPAL]]<0, "No vencido", IF(AND(COMPOSICIONSALDOneo[[#This Row],[FECHA VTO.]]-TODAY()>=1, COMPOSICIONSALDOneo[[#This Row],[FECHA VTO.]]-TODAY()<=5), "Vence 2-5 días", IF(COMPOSICIONSALDOneo[[#This Row],[FECHA VTO.]]-TODAY()<0, "Vencido", "No vencido"))) -> Vencido
A35: NDVI | B35: 46075 | C35: Cliente 57 | D35: FC-1033 | E35: OT reparacion | F35: Dólar Divisa | G35: 150.59 | H35: 1 | I35: 150.59 | J35: 150.59 | K35: 46103 | L35: =IF(COMPOSICIONSALDOneo[[#This Row],[IMP. PRINCIPAL]] > 0, MAX(0, $A$1-COMPOSICIONSALDOneo[[#This Row],[FECHA VTO.]]), 0) -> 103 | M35: =UPPER(TEXT(COMPOSICIONSALDOneo[[#This Row],[FECHA VTO.]],"MMM")) -> MAR | N35: =TEXT(MONTH(COMPOSICIONSALDOneo[[#This Row],[FECHA VTO.]]),"00") -> 03 | O35: =+CONCATENATE(COMPOSICIONSALDOneo[[#This Row],[FECH]],"-",COMPOSICIONSALDOneo[[#This Row],[MES2]]) -> MAR-03 | P35: =IF(L35=0,"NO VENCIDO",IF(L35<30,"VENCIDO<30",IF(L35<60,"VENCIDO 30",IF(L35<90,"VENCIDO 60",IF(L35<150,"VENCIDO 90","VENCIDO>150"))))) -> VENCIDO 90 | Q35: =IF(COMPOSICIONSALDOneo[[#This Row],[DIAS DE MORA]]<1,"NO VENCIDO",IF(COMPOSICIONSALDOneo[[#This Row],[DIAS DE MORA]]>=1,"VENCIDO","INCOBRABLE")) -> VENCIDO | R35: =+VLOOKUP(COMPOSICIONSALDOneo[[#This Row],[Documento tipo]],Tabla7[#All],2,0) -> COBRANZAS | S35: =+VLOOKUP(COMPOSICIONSALDOneo[[#This Row],[CLIENTE]],Tabla5[],3,FALSE) -> Catamarca | T35: =IF(COMPOSICIONSALDOneo[[#This Row],[IMP. PRINCIPAL]]<0, "No vencido", IF(AND(COMPOSICIONSALDOneo[[#This Row],[FECHA VTO.]]-TODAY()>=1, COMPOSICIONSALDOneo[[#This Row],[FECHA VTO.]]-TODAY()<=5), "Vence 2-5 días", IF(COMPOSICIONSALDOneo[[#This Row],[FECHA VTO.]]-TODAY()<0, "Vencido", "No vencido"))) -> Vencido
A36: COBRANZA | B36: 46113 | C36: Cliente 23 | D36: FC-1034 | E36: Facturacion mensual | F36: Dólares | G36: 365.01 | H36: 1 | I36: 365.01 | J36: 365.01 | K36: 46139 | L36: =IF(COMPOSICIONSALDOneo[[#This Row],[IMP. PRINCIPAL]] > 0, MAX(0, $A$1-COMPOSICIONSALDOneo[[#This Row],[FECHA VTO.]]), 0) -> 67 | M36: =UPPER(TEXT(COMPOSICIONSALDOneo[[#This Row],[FECHA VTO.]],"MMM")) -> ABR | N36: =TEXT(MONTH(COMPOSICIONSALDOneo[[#This Row],[FECHA VTO.]]),"00") -> 04 | O36: =+CONCATENATE(COMPOSICIONSALDOneo[[#This Row],[FECH]],"-",COMPOSICIONSALDOneo[[#This Row],[MES2]]) -> ABR-04 | P36: =IF(L36=0,"NO VENCIDO",IF(L36<30,"VENCIDO<30",IF(L36<60,"VENCIDO 30",IF(L36<90,"VENCIDO 60",IF(L36<150,"VENCIDO 90","VENCIDO>150"))))) -> VENCIDO 60 | Q36: =IF(COMPOSICIONSALDOneo[[#This Row],[DIAS DE MORA]]<1,"NO VENCIDO",IF(COMPOSICIONSALDOneo[[#This Row],[DIAS DE MORA]]>=1,"VENCIDO","INCOBRABLE")) -> VENCIDO | R36: =+VLOOKUP(COMPOSICIONSALDOneo[[#This Row],[Documento tipo]],Tabla7[#All],2,0) -> COBRANZAS | S36: =+VLOOKUP(COMPOSICIONSALDOneo[[#This Row],[CLIENTE]],Tabla5[],3,FALSE) -> Tucuman | T36: =IF(COMPOSICIONSALDOneo[[#This Row],[IMP. PRINCIPAL]]<0, "No vencido", IF(AND(COMPOSICIONSALDOneo[[#This Row],[FECHA VTO.]]-TODAY()>=1, COMPOSICIONSALDOneo[[#This Row],[FECHA VTO.]]-TODAY()<=5), "Vence 2-5 días", IF(COMPOSICIONSALDOneo[[#This Row],[FECHA VTO.]]-TODAY()<0, "Vencido", "No vencido"))) -> Vencido
A37: NCV | B37: 46082 | C37: Cliente 5 | D37: FC-1035 | E37: Service programado | F37: Pesos | G37: 161.27 | H37: 1058.81 | I37: 161.27 | J37: 161.27 | K37: 46107 | L37: =IF(COMPOSICIONSALDOneo[[#This Row],[IMP. PRINCIPAL]] > 0, MAX(0, $A$1-COMPOSICIONSALDOneo[[#This Row],[FECHA VTO.]]), 0) -> 99 | M37: =UPPER(TEXT(COMPOSICIONSALDOneo[[#This Row],[FECHA VTO.]],"MMM")) -> MAR | N37: =TEXT(MONTH(COMPOSICIONSALDOneo[[#This Row],[FECHA VTO.]]),"00") -> 03 | O37: =+CONCATENATE(COMPOSICIONSALDOneo[[#This Row],[FECH]],"-",COMPOSICIONSALDOneo[[#This Row],[MES2]]) -> MAR-03 | P37: =IF(L37=0,"NO VENCIDO",IF(L37<30,"VENCIDO<30",IF(L37<60,"VENCIDO 30",IF(L37<90,"VENCIDO 60",IF(L37<150,"VENCIDO 90","VENCIDO>150"))))) -> VENCIDO 90 | Q37: =IF(COMPOSICIONSALDOneo[[#This Row],[DIAS DE MORA]]<1,"NO VENCIDO",IF(COMPOSICIONSALDOneo[[#This Row],[DIAS DE MORA]]>=1,"VENCIDO","INCOBRABLE")) -> VENCIDO | R37: =+VLOOKUP(COMPOSICIONSALDOneo[[#This Row],[Documento tipo]],Tabla7[#All],2,0) -> REPUESTOS | S37: =+VLOOKUP(COMPOSICIONSALDOneo[[#This Row],[CLIENTE]],Tabla5[],3,FALSE) -> Jujuy | T37: =IF(COMPOSICIONSALDOneo[[#This Row],[IMP. PRINCIPAL]]<0, "No vencido", IF(AND(COMPOSICIONSALDOneo[[#This Row],[FECHA VTO.]]-TODAY()>=1, COMPOSICIONSALDOneo[[#This Row],[FECHA VTO.]]-TODAY()<=5), "Vence 2-5 días", IF(COMPOSICIONSALDOneo[[#This Row],[FECHA VTO.]]-TODAY()<0, "Vencido", "No vencido"))) -> Vencido
A38: NCV | B38: 46139 | C38: Cliente 13 | D38: FC-1036 | E38: Venta repuestos | F38: Dólares | G38: 1463.69 | H38: 1 | I38: 1463.69 | J38: 1463.69 | K38: 46166 | L38: =IF(COMPOSICIONSALDOneo[[#This Row],[IMP. PRINCIPAL]] > 0, MAX(0, $A$1-COMPOSICIONSALDOneo[[#This Row],[FECHA VTO.]]), 0) -> 40 | M38: =UPPER(TEXT(COMPOSICIONSALDOneo[[#This Row],[FECHA VTO.]],"MMM")) -> MAY | N38: =TEXT(MONTH(COMPOSICIONSALDOneo[[#This Row],[FECHA VTO.]]),"00") -> 05 | O38: =+CONCATENATE(COMPOSICIONSALDOneo[[#This Row],[FECH]],"-",COMPOSICIONSALDOneo[[#This Row],[MES2]]) -> MAY-05 | P38: =IF(L38=0,"NO VENCIDO",IF(L38<30,"VENCIDO<30",IF(L38<60,"VENCIDO 30",IF(L38<90,"VENCIDO 60",IF(L38<150,"VENCIDO 90","VENCIDO>150"))))) -> VENCIDO 30 | Q38: =IF(COMPOSICIONSALDOneo[[#This Row],[DIAS DE MORA]]<1,"NO VENCIDO",IF(COMPOSICIONSALDOneo[[#This Row],[DIAS DE MORA]]>=1,"VENCIDO","INCOBRABLE")) -> VENCIDO | R38: =+VLOOKUP(COMPOSICIONSALDOneo[[#This Row],[Documento tipo]],Tabla7[#All],2,0) -> REPUESTOS | S38: =+VLOOKUP(COMPOSICIONSALDOneo[[#This Row],[CLIENTE]],Tabla5[],3,FALSE) -> Tucuman | T38: =IF(COMPOSICIONSALDOneo[[#This Row],[IMP. PRINCIPAL]]<0, "No vencido", IF(AND(COMPOSICIONSALDOneo[[#This Row],[FECHA VTO.]]-TODAY()>=1, COMPOSICIONSALDOneo[[#This Row],[FECHA VTO.]]-TODAY()<=5), "Vence 2-5 días", IF(COMPOSICIONSALDOneo[[#This Row],[FECHA VTO.]]-TODAY()<0, "Vencido", "No vencido"))) -> Vencido
A39: FCEMIPYME_REP_REFAC | B39: 46214 | C39: Cliente 34 | D39: FC-1037 | E39: Alquiler equipo | F39: Pesos | G39: 7109.09 | H39: 1012.09 | I39: 7109.09 | J39: 7109.09 | K39: 46244 | L39: =IF(COMPOSICIONSALDOneo[[#This Row],[IMP. PRINCIPAL]] > 0, MAX(0, $A$1-COMPOSICIONSALDOneo[[#This Row],[FECHA VTO.]]), 0) -> 0 | M39: =UPPER(TEXT(COMPOSICIONSALDOneo[[#This Row],[FECHA VTO.]],"MMM")) -> AGO | N39: =TEXT(MONTH(COMPOSICIONSALDOneo[[#This Row],[FECHA VTO.]]),"00") -> 08 | O39: =+CONCATENATE(COMPOSICIONSALDOneo[[#This Row],[FECH]],"-",COMPOSICIONSALDOneo[[#This Row],[MES2]]) -> AGO-08 | P39: =IF(L39=0,"NO VENCIDO",IF(L39<30,"VENCIDO<30",IF(L39<60,"VENCIDO 30",IF(L39<90,"VENCIDO 60",IF(L39<150,"VENCIDO 90","VENCIDO>150"))))) -> NO VENCIDO | Q39: =IF(COMPOSICIONSALDOneo[[#This Row],[DIAS DE MORA]]<1,"NO VENCIDO",IF(COMPOSICIONSALDOneo[[#This Row],[DIAS DE MORA]]>=1,"VENCIDO","INCOBRABLE")) -> NO VENCIDO | R39: =+VLOOKUP(COMPOSICIONSALDOneo[[#This Row],[Documento tipo]],Tabla7[#All],2,0) -> REPUESTOS | S39: =+VLOOKUP(COMPOSICIONSALDOneo[[#This Row],[CLIENTE]],Tabla5[],3,FALSE) -> Jujuy | T39: =IF(COMPOSICIONSALDOneo[[#This Row],[IMP. PRINCIPAL]]<0, "No vencido", IF(AND(COMPOSICIONSALDOneo[[#This Row],[FECHA VTO.]]-TODAY()>=1, COMPOSICIONSALDOneo[[#This Row],[FECHA VTO.]]-TODAY()<=5), "Vence 2-5 días", IF(COMPOSICIONSALDOneo[[#This Row],[FECHA VTO.]]-TODAY()<0, "Vencido", "No vencido"))) -> No vencido
A40: FCELIGA | B40: 46181 | C40: Cliente 17 | D40: FC-1038 | E40: Service programado | F40: Pesos | G40: 17386.83 | H40: 1033.36 | I40: 17386.83 | J40: 17386.83 | K40: 46219 | L40: =IF(COMPOSICIONSALDOneo[[#This Row],[IMP. PRINCIPAL]] > 0, MAX(0, $A$1-COMPOSICIONSALDOneo[[#This Row],[FECHA VTO.]]), 0) -> 0 | M40: =UPPER(TEXT(COMPOSICIONSALDOneo[[#This Row],[FECHA VTO.]],"MMM")) -> JUL | N40: =TEXT(MONTH(COMPOSICIONSALDOneo[[#This Row],[FECHA VTO.]]),"00") -> 07 | O40: =+CONCATENATE(COMPOSICIONSALDOneo[[#This Row],[FECH]],"-",COMPOSICIONSALDOneo[[#This Row],[MES2]]) -> JUL-07 | P40: =IF(L40=0,"NO VENCIDO",IF(L40<30,"VENCIDO<30",IF(L40<60,"VENCIDO 30",IF(L40<90,"VENCIDO 60",IF(L40<150,"VENCIDO 90","VENCIDO>150"))))) -> NO VENCIDO | Q40: =IF(COMPOSICIONSALDOneo[[#This Row],[DIAS DE MORA]]<1,"NO VENCIDO",IF(COMPOSICIONSALDOneo[[#This Row],[DIAS DE MORA]]>=1,"VENCIDO","INCOBRABLE")) -> NO VENCIDO | R40: =+VLOOKUP(COMPOSICIONSALDOneo[[#This Row],[Documento tipo]],Tabla7[#All],2,0) -> REPUESTOS | S40: =+VLOOKUP(COMPOSICIONSALDOneo[[#This Row],[CLIENTE]],Tabla5[],3,FALSE) -> Jujuy | T40: =IF(COMPOSICIONSALDOneo[[#This Row],[IMP. PRINCIPAL]]<0, "No vencido", IF(AND(COMPOSICIONSALDOneo[[#This Row],[FECHA VTO.]]-TODAY()>=1, COMPOSICIONSALDOneo[[#This Row],[FECHA VTO.]]-TODAY()<=5), "Vence 2-5 días", IF(COMPOSICIONSALDOneo[[#This Row],[FECHA VTO.]]-TODAY()<0, "Vencido", "No vencido"))) -> No vencido
A41: NCCEMIPYME-MAQ | B41: 46006 | C41: Cliente 20 | D41: FC-1039 | E41: Insumos varios | F41: Dólares | G41: 363.53 | H41: 1 | I41: 363.53 | J41: 363.53 | K41: 46044 | L41: =IF(COMPOSICIONSALDOneo[[#This Row],[IMP. PRINCIPAL]] > 0, MAX(0, $A$1-COMPOSICIONSALDOneo[[#This Row],[FECHA VTO.]]), 0) -> 162 | M41: =UPPER(TEXT(COMPOSICIONSALDOneo[[#This Row],[FECHA VTO.]],"MMM")) -> ENE | N41: =TEXT(MONTH(COMPOSICIONSALDOneo[[#This Row],[FECHA VTO.]]),"00") -> 01 | O41: =+CONCATENATE(COMPOSICIONSALDOneo[[#This Row],[FECH]],"-",COMPOSICIONSALDOneo[[#This Row],[MES2]]) -> ENE-01 | P41: =IF(L41=0,"NO VENCIDO",IF(L41<30,"VENCIDO<30",IF(L41<60,"VENCIDO 30",IF(L41<90,"VENCIDO 60",IF(L41<150,"VENCIDO 90","VENCIDO>150"))))) -> VENCIDO>150 | Q41: =IF(COMPOSICIONSALDOneo[[#This Row],[DIAS DE MORA]]<1,"NO VENCIDO",IF(COMPOSICIONSALDOneo[[#This Row],[DIAS DE MORA]]>=1,"VENCIDO","INCOBRABLE")) -> VENCIDO | R41: =+VLOOKUP(COMPOSICIONSALDOneo[[#This Row],[Documento tipo]],Tabla7[#All],2,0) -> MAQUINAS | S41: =+VLOOKUP(COMPOSICIONSALDOneo[[#This Row],[CLIENTE]],Tabla5[],3,FALSE) -> Jujuy | T41: =IF(COMPOSICIONSALDOneo[[#This Row],[IMP. PRINCIPAL]]<0, "No vencido", IF(AND(COMPOSICIONSALDOneo[[#This Row],[FECHA VTO.]]-TODAY()>=1, COMPOSICIONSALDOneo[[#This Row],[FECHA VTO.]]-TODAY()<=5), "Vence 2-5 días", IF(COMPOSICIONSALDOneo[[#This Row],[FECHA VTO.]]-TODAY()<0, "Vencido", "No vencido"))) -> Vencido
A42: NDMANUAL | B42: 46223 | C42: Cliente 36 | D42: FC-1040 | E42: Mantenimiento | F42: Pesos | G42: 14991.32 | H42: 1063.7 | I42: 14991.32 | J42: 14991.32 | K42: 46249 | L42: =IF(COMPOSICIONSALDOneo[[#This Row],[IMP. PRINCIPAL]] > 0, MAX(0, $A$1-COMPOSICIONSALDOneo[[#This Row],[FECHA VTO.]]), 0) -> 0 | M42: =UPPER(TEXT(COMPOSICIONSALDOneo[[#This Row],[FECHA VTO.]],"MMM")) -> AGO | N42: =TEXT(MONTH(COMPOSICIONSALDOneo[[#This Row],[FECHA VTO.]]),"00") -> 08 | O42: =+CONCATENATE(COMPOSICIONSALDOneo[[#This Row],[FECH]],"-",COMPOSICIONSALDOneo[[#This Row],[MES2]]) -> AGO-08 | P42: =IF(L42=0,"NO VENCIDO",IF(L42<30,"VENCIDO<30",IF(L42<60,"VENCIDO 30",IF(L42<90,"VENCIDO 60",IF(L42<150,"VENCIDO 90","VENCIDO>150"))))) -> NO VENCIDO | Q42: =IF(COMPOSICIONSALDOneo[[#This Row],[DIAS DE MORA]]<1,"NO VENCIDO",IF(COMPOSICIONSALDOneo[[#This Row],[DIAS DE MORA]]>=1,"VENCIDO","INCOBRABLE")) -> NO VENCIDO | R42: =+VLOOKUP(COMPOSICIONSALDOneo[[#This Row],[Documento tipo]],Tabla7[#All],2,0) -> COBRANZAS | S42: =+VLOOKUP(COMPOSICIONSALDOneo[[#This Row],[CLIENTE]],Tabla5[],3,FALSE) -> Jujuy | T42: =IF(COMPOSICIONSALDOneo[[#This Row],[IMP. PRINCIPAL]]<0, "No vencido", IF(AND(COMPOSICIONSALDOneo[[#This Row],[FECHA VTO.]]-TODAY()>=1, COMPOSICIONSALDOneo[[#This Row],[FECHA VTO.]]-TODAY()<=5), "Vence 2-5 días", IF(COMPOSICIONSALDOneo[[#This Row],[FECHA VTO.]]-TODAY()<0, "Vencido", "No vencido"))) -> No vencido
A43: NDMANUAL | B43: 46206 | C43: Cliente 19 | D43: FC-1041 | E43: Venta maquina | F43: Dólar Divisa | G43: 1131.96 | H43: 1 | I43: 1131.96 | J43: 1131.96 | K43: 46230 | L43: =IF(COMPOSICIONSALDOneo[[#This Row],[IMP. PRINCIPAL]] > 0, MAX(0, $A$1-COMPOSICIONSALDOneo[[#This Row],[FECHA VTO.]]), 0) -> 0 | M43: =UPPER(TEXT(COMPOSICIONSALDOneo[[#This Row],[FECHA VTO.]],"MMM")) -> JUL | N43: =TEXT(MONTH(COMPOSICIONSALDOneo[[#This Row],[FECHA VTO.]]),"00") -> 07 | O43: =+CONCATENATE(COMPOSICIONSALDOneo[[#This Row],[FECH]],"-",COMPOSICIONSALDOneo[[#This Row],[MES2]]) -> JUL-07 | P43: =IF(L43=0,"NO VENCIDO",IF(L43<30,"VENCIDO<30",IF(L43<60,"VENCIDO 30",IF(L43<90,"VENCIDO 60",IF(L43<150,"VENCIDO 90","VENCIDO>150"))))) -> NO VENCIDO | Q43: =IF(COMPOSICIONSALDOneo[[#This Row],[DIAS DE MORA]]<1,"NO VENCIDO",IF(COMPOSICIONSALDOneo[[#This Row],[DIAS DE MORA]]>=1,"VENCIDO","INCOBRABLE")) -> NO VENCIDO | R43: =+VLOOKUP(COMPOSICIONSALDOneo[[#This Row],[Documento tipo]],Tabla7[#All],2,0) -> COBRANZAS | S43: =+VLOOKUP(COMPOSICIONSALDOneo[[#This Row],[CLIENTE]],Tabla5[],3,FALSE) -> Jujuy | T43: =IF(COMPOSICIONSALDOneo[[#This Row],[IMP. PRINCIPAL]]<0, "No vencido", IF(AND(COMPOSICIONSALDOneo[[#This Row],[FECHA VTO.]]-TODAY()>=1, COMPOSICIONSALDOneo[[#This Row],[FECHA VTO.]]-TODAY()<=5), "Vence 2-5 días", IF(COMPOSICIONSALDOneo[[#This Row],[FECHA VTO.]]-TODAY()<0, "Vencido", "No vencido"))) -> No vencido
A44: RCM | B44: 46133 | C44: Cliente 34 | D44: FC-1042 | E44: Alquiler equipo | F44: Pesos | G44: 1870.43 | H44: 1080.8 | I44: 1870.43 | J44: 1870.43 | K44: 46161 | L44: =IF(COMPOSICIONSALDOneo[[#This Row],[IMP. PRINCIPAL]] > 0, MAX(0, $A$1-COMPOSICIONSALDOneo[[#This Row],[FECHA VTO.]]), 0) -> 45 | M44: =UPPER(TEXT(COMPOSICIONSALDOneo[[#This Row],[FECHA VTO.]],"MMM")) -> MAY | N44: =TEXT(MONTH(COMPOSICIONSALDOneo[[#This Row],[FECHA VTO.]]),"00") -> 05 | O44: =+CONCATENATE(COMPOSICIONSALDOneo[[#This Row],[FECH]],"-",COMPOSICIONSALDOneo[[#This Row],[MES2]]) -> MAY-05 | P44: =IF(L44=0,"NO VENCIDO",IF(L44<30,"VENCIDO<30",IF(L44<60,"VENCIDO 30",IF(L44<90,"VENCIDO 60",IF(L44<150,"VENCIDO 90","VENCIDO>150"))))) -> VENCIDO 30 | Q44: =IF(COMPOSICIONSALDOneo[[#This Row],[DIAS DE MORA]]<1,"NO VENCIDO",IF(COMPOSICIONSALDOneo[[#This Row],[DIAS DE MORA]]>=1,"VENCIDO","INCOBRABLE")) -> VENCIDO | R44: =+VLOOKUP(COMPOSICIONSALDOneo[[#This Row],[Documento tipo]],Tabla7[#All],2,0) -> MAQUINAS | S44: =+VLOOKUP(COMPOSICIONSALDOneo[[#This Row],[CLIENTE]],Tabla5[],3,FALSE) -> Jujuy | T44: =IF(COMPOSICIONSALDOneo[[#This Row],[IMP. PRINCIPAL]]<0, "No vencido", IF(AND(COMPOSICIONSALDOneo[[#This Row],[FECHA VTO.]]-TODAY()>=1, COMPOSICIONSALDOneo[[#This Row],[FECHA VTO.]]-TODAY()<=5), "Vence 2-5 días", IF(COMPOSICIONSALDOneo[[#This Row],[FECHA VTO.]]-TODAY()<0, "Vencido", "No vencido"))) -> Vencido
A45: FDVAM | B45: 46216 | C45: Cliente 7 | D45: FC-1043 | E45: Servicio de PM | F45: Dólar Divisa | G45: 1882.05 | H45: 1 | I45: 1882.05 | J45: 1882.05 | K45: 46253 | L45: =IF(COMPOSICIONSALDOneo[[#This Row],[IMP. PRINCIPAL]] > 0, MAX(0, $A$1-COMPOSICIONSALDOneo[[#This Row],[FECHA VTO.]]), 0) -> 0 | M45: =UPPER(TEXT(COMPOSICIONSALDOneo[[#This Row],[FECHA VTO.]],"MMM")) -> AGO | N45: =TEXT(MONTH(COMPOSICIONSALDOneo[[#This Row],[FECHA VTO.]]),"00") -> 08 | O45: =+CONCATENATE(COMPOSICIONSALDOneo[[#This Row],[FECH]],"-",COMPOSICIONSALDOneo[[#This Row],[MES2]]) -> AGO-08 | P45: =IF(L45=0,"NO VENCIDO",IF(L45<30,"VENCIDO<30",IF(L45<60,"VENCIDO 30",IF(L45<90,"VENCIDO 60",IF(L45<150,"VENCIDO 90","VENCIDO>150"))))) -> NO VENCIDO | Q45: =IF(COMPOSICIONSALDOneo[[#This Row],[DIAS DE MORA]]<1,"NO VENCIDO",IF(COMPOSICIONSALDOneo[[#This Row],[DIAS DE MORA]]>=1,"VENCIDO","INCOBRABLE")) -> NO VENCIDO | R45: =+VLOOKUP(COMPOSICIONSALDOneo[[#This Row],[Documento tipo]],Tabla7[#All],2,0) -> MAQUINAS | S45: =+VLOOKUP(COMPOSICIONSALDOneo[[#This Row],[CLIENTE]],Tabla5[],3,FALSE) -> Catamarca | T45: =IF(COMPOSICIONSALDOneo[[#This Row],[IMP. PRINCIPAL]]<0, "No vencido", IF(AND(COMPOSICIONSALDOneo[[#This Row],[FECHA VTO.]]-TODAY()>=1, COMPOSICIONSALDOneo[[#This Row],[FECHA VTO.]]-TODAY()<=5), "Vence 2-5 días", IF(COMPOSICIONSALDOneo[[#This Row],[FECHA VTO.]]-TODAY()<0, "Vencido", "No vencido"))) -> No vencido
A46: FDVAM | B46: 46234 | C46: Cliente 2 | D46: FC-1044 | E46: Service programado | F46: Dólares | G46: 12434.04 | H46: 1 | I46: 12434.04 | J46: 12434.04 | K46: 46256 | L46: =IF(COMPOSICIONSALDOneo[[#This Row],[IMP. PRINCIPAL]] > 0, MAX(0, $A$1-COMPOSICIONSALDOneo[[#This Row],[FECHA VTO.]]), 0) -> 0 | M46: =UPPER(TEXT(COMPOSICIONSALDOneo[[#This Row],[FECHA VTO.]],"MMM")) -> AGO | N46: =TEXT(MONTH(COMPOSICIONSALDOneo[[#This Row],[FECHA VTO.]]),"00") -> 08 | O46: =+CONCATENATE(COMPOSICIONSALDOneo[[#This Row],[FECH]],"-",COMPOSICIONSALDOneo[[#This Row],[MES2]]) -> AGO-08 | P46: =IF(L46=0,"NO VENCIDO",IF(L46<30,"VENCIDO<30",IF(L46<60,"VENCIDO 30",IF(L46<90,"VENCIDO 60",IF(L46<150,"VENCIDO 90","VENCIDO>150"))))) -> NO VENCIDO | Q46: =IF(COMPOSICIONSALDOneo[[#This Row],[DIAS DE MORA]]<1,"NO VENCIDO",IF(COMPOSICIONSALDOneo[[#This Row],[DIAS DE MORA]]>=1,"VENCIDO","INCOBRABLE")) -> NO VENCIDO | R46: =+VLOOKUP(COMPOSICIONSALDOneo[[#This Row],[Documento tipo]],Tabla7[#All],2,0) -> MAQUINAS | S46: =+VLOOKUP(COMPOSICIONSALDOneo[[#This Row],[CLIENTE]],Tabla5[],3,FALSE) -> Santiago del Estero | T46: =IF(COMPOSICIONSALDOneo[[#This Row],[IMP. PRINCIPAL]]<0, "No vencido", IF(AND(COMPOSICIONSALDOneo[[#This Row],[FECHA VTO.]]-TODAY()>=1, COMPOSICIONSALDOneo[[#This Row],[FECHA VTO.]]-TODAY()<=5), "Vence 2-5 días", IF(COMPOSICIONSALDOneo[[#This Row],[FECHA VTO.]]-TODAY()<0, "Vencido", "No vencido"))) -> No vencido
... A63: FCEMIPYME-MAQ | B63: 46140 | C63: Cliente 55 | D63: FC-1061 | E63: Insumos varios | F63: Dólar Divisa | G63: 1574.21 | H63: 1 | I63: 1574.21 | J63: 1574.21 | K63: 46161 | L63: =IF(COMPOSICIONSALDOneo[[#This Row],[IMP. PRINCIPAL]] > 0, MAX(0, $A$1-COMPOSICIONSALDOneo[[#This Row],[FECHA VTO.]]), 0) -> 45 | M63: =UPPER(TEXT(COMPOSICIONSALDOneo[[#This Row],[FECHA VTO.]],"MMM")) -> MAY | N63: =TEXT(MONTH(COMPOSICIONSALDOneo[[#This Row],[FECHA VTO.]]),"00") -> 05 | O63: =+CONCATENATE(COMPOSICIONSALDOneo[[#This Row],[FECH]],"-",COMPOSICIONSALDOneo[[#This Row],[MES2]]) -> MAY-05 | P63: =IF(L63=0,"NO VENCIDO",IF(L63<30,"VENCIDO<30",IF(L63<60,"VENCIDO 30",IF(L63<90,"VENCIDO 60",IF(L63<150,"VENCIDO 90","VENCIDO>150"))))) -> VENCIDO 30 | Q63: =IF(COMPOSICIONSALDOneo[[#This Row],[DIAS DE MORA]]<1,"NO VENCIDO",IF(COMPOSICIONSALDOneo[[#This Row],[DIAS DE MORA]]>=1,"VENCIDO","INCOBRABLE")) -> VENCIDO | R63: =+VLOOKUP(COMPOSICIONSALDOneo[[#This Row],[Documento tipo]],Tabla7[#All],2,0) -> MAQUINAS | S63: =+VLOOKUP(COMPOSICIONSALDOneo[[#This Row],[CLIENTE]],Tabla5[],3,FALSE) -> Jujuy | T63: =IF(COMPOSICIONSALDOneo[[#This Row],[IMP. PRINCIPAL]]<0, "No vencido", IF(AND(COMPOSICIONSALDOneo[[#This Row],[FECHA VTO.]]-TODAY()>=1, COMPOSICIONSALDOneo[[#This Row],[FECHA VTO.]]-TODAY()<=5), "Vence 2-5 días", IF(COMPOSICIONSALDOneo[[#This Row],[FECHA VTO.]]-TODAY()<0, "Vencido", "No vencido"))) -> Vencido

Sheet Historico Cartera 2026
A1: HISTÓRICO MENSUAL — DASHBOARD COBRANZAS SUC NOA
A2: Cargar manualmente una fila por mes. Indicador clave: columna E (% Cartera Vencida / Total).
A3: Fecha Corte | B3: Mes | C3: Total Cartera (USD) | D3: Cartera Vencida (USD) | E3: % Cartera Vencida / Total | F3: Var. p.p. vs mes anterior | G3: Prom. Vencido (días) | H3: Var. días vs mes anterior | I3: % Incobrables | J3: Var. p.p. vs mes anterior | L3: Obj. 30 días | M3: Obj. 0,5% Incob.
A4: 46053 | B4: Ene | C4: 330415 | D4: 205444 | E4: =IFERROR(D4/C4,"-") -> 0.62177565 | F4: - | G4: 25.8 | H4: - | I4: 0 | J4: - | L4: 30 | M4: 0.005
A5: 46081 | B5: Feb | C5: 207482 | D5: 88198 | E5: =IFERROR(D5/C5,"-") -> 0.42508748 | F5: =IF(E5="","-",IFERROR(E5-E4,"-")) -> -0.19668817 | G5: 27.1 | H5: =IF(G5="","-",IFERROR(G5-G4,"-")) -> 1.3 | I5: 0 | J5: =IF(I5="","-",IFERROR(I5-I4,"-")) -> 0 | L5: 30 | M5: 0.005
A6: 46112 | B6: Mar | C6: 198795 | D6: 127627 | E6: =IFERROR(D6/C6,"-") -> 0.64200307 | F6: =IF(E6="","-",IFERROR(E6-E5,"-")) -> 0.21691559 | G6: 28.5 | H6: =IF(G6="","-",IFERROR(G6-G5,"-")) -> 1.4 | I6: 0.0003 | J6: =IF(I6="","-",IFERROR(I6-I5,"-")) -> 0.0003 | L6: 30 | M6: 0.005
A7: 46142 | B7: Abr | C7: 237477 | D7: 132384 | E7: =IFERROR(D7/C7,"-") -> 0.5574603 | F7: =IF(E7="","-",IFERROR(E7-E6,"-")) -> -0.084542767 | G7: 31.5 | H7: =IF(G7="","-",IFERROR(G7-G6,"-")) -> 3 | I7: 0.0029 | J7: =IF(I7="","-",IFERROR(I7-I6,"-")) -> 0.0026 | L7: 30 | M7: 0.005
A8: 46173 | B8: May | C8: 342893 | D8: 214337 | E8: =IFERROR(D8/C8,"-") -> 0.62508421 | F8: =IF(E8="","-",IFERROR(E8-E7,"-")) -> 0.067623909 | G8: 31.5 | H8: =IF(G8="","-",IFERROR(G8-G7,"-")) -> 0 | I8: 0.0011 | J8: =IF(I8="","-",IFERROR(I8-I7,"-")) -> -0.0018 | L8: 30 | M8: 0.005
A9: 46203 | B9: Jun | C9: 310066 | D9: 72956 | E9: =IFERROR(D9/C9,"-") -> 0.23529184 | F9: =IF(E9="","-",IFERROR(E9-E8,"-")) -> -0.38979237 | G9: 26.1 | H9: =IF(G9="","-",IFERROR(G9-G8,"-")) -> -5.4 | I9: 0.0015 | J9: =IF(I9="","-",IFERROR(I9-I8,"-")) -> 0.0004 | L9: 30 | M9: 0.005
A10: 46234 | B10: Jul | E10: =IF(C10="","-",IFERROR(D10/C10,"-")) -> - | F10: =IF(E10="","-",IFERROR(E10-E9,"-")) -> - | H10: =IF(G10="","-",IFERROR(G10-G9,"-")) -> - | J10: =IF(I10="","-",IFERROR(I10-I9,"-")) -> - | L10: 30 | M10: 0.005
A11: 46265 | B11: Ago | E11: =IF(C11="","-",IFERROR(D11/C11,"-")) -> - | F11: =IF(E11="","-",IFERROR(E11-E10,"-")) -> - | H11: =IF(G11="","-",IFERROR(G11-G10,"-")) -> - | J11: =IF(I11="","-",IFERROR(I11-I10,"-")) -> - | L11: 30 | M11: 0.005
A12: 46295 | B12: Sept | E12: =IF(C12="","-",IFERROR(D12/C12,"-")) -> - | F12: =IF(E12="","-",IFERROR(E12-E11,"-")) -> - | H12: =IF(G12="","-",IFERROR(G12-G11,"-")) -> - | J12: =IF(I12="","-",IFERROR(I12-I11,"-")) -> - | L12: 30 | M12: 0.005
A13: 46326 | B13: Oct | E13: =IF(C13="","-",IFERROR(D13/C13,"-")) -> - | F13: =IF(E13="","-",IFERROR(E13-E12,"-")) -> - | H13: =IF(G13="","-",IFERROR(G13-G12,"-")) -> - | J13: =IF(I13="","-",IFERROR(I13-I12,"-")) -> - | L13: 30 | M13: 0.005
A14: 46356 | B14: Nov | F14: =IF(E14="","-",IFERROR(E14-E13,"-")) -> - | H14: =IF(G14="","-",IFERROR(G14-G13,"-")) -> - | J14: =IF(I14="","-",IFERROR(I14-I13,"-")) -> - | L14: 30 | M14: 0.005
A15: 46387 | B15: Dic | E15: =IF(C15="","-",IFERROR(D15/C15,"-")) -> - | F15: =IF(E15="","-",IFERROR(E15-E13,"-")) -> - | H15: =IF(G15="","-",IFERROR(G15-G13,"-")) -> - | J15: =IF(I15="","-",IFERROR(I15-I13,"-")) -> - | L15: 30 | M15: 0.005

Sheet Kpis actual
A1: KPIs PARA PEGAR EN EL DASHBOARD AL CIERRE
A3: KPI | B3: Valor actual | C3: Variación | D3: Var. Mes ant.
A4: % Cartera Vencida / Total | B4: =INDEX('Historico Cartera 2026'!E4:E9,COUNTA('Historico Cartera 2026'!E4:E9)) -> 0.23529184 | C4: =INDEX('Historico Cartera 2026'!F5:F9,COUNTA('Historico Cartera 2026'!F5:F9)) -> -0.38979237 | D4: =TEXT(B4,"0,0%")&" "&IF(C4>0,"▲ +","▼ ")&TEXT(ABS(C4),"0,0%") -> 23,5% ▼ 39,0%
A5: Cartera Vencida (USD) | B5: =INDEX('Historico Cartera 2026'!D4:D9,COUNTA('Historico Cartera 2026'!D4:D9)) -> 72956 | D5: =TEXT(B5,"$#.##0") -> $72.956
A6: Total Cartera (referencia) | B6: =INDEX('Historico Cartera 2026'!C4:C9,COUNTA('Historico Cartera 2026'!C4:C9)) -> 310066 | D6: =TEXT(B6,"$#.##0") -> $310.066
A7: Prom. Vencido (días) | B7: =INDEX('Historico Cartera 2026'!G4:G9,COUNTA('Historico Cartera 2026'!G4:G9)) -> 26.1 | C7: =INDEX('Historico Cartera 2026'!H5:H9,COUNTA('Historico Cartera 2026'!H5:H9)) -> -5.4 | D7: =B7&" días "&IF(C7=0,"= cierre ant.",IF(C7>0,"▲ +"&TEXT(C7,"0")&" días","▼ "&TEXT(ABS(C7),"0")&" días")) -> 26,1 días ▼ 5 días
A8: % Incobrables | B8: =INDEX('Historico Cartera 2026'!I4:I9,COUNTA('Historico Cartera 2026'!I4:I9)) -> 0.0015 | C8: =INDEX('Historico Cartera 2026'!J5:J9,COUNTA('Historico Cartera 2026'!J5:J9)) -> 0.0004 | D8: =TEXT(B8,"0,00%")&" "&IF(C8=0,"= cierre ant.",IF(C8>0,"▲ +"&TEXT(ABS(C8),"0,00%"),"▼ "&TEXT(ABS(C8),"0,00%"))) -> 0,15% ▲ +0,04%
